[{"deviceLocation": "150995745", "locations": [{"directDeviceLocation": "150995733", "direction": [{"isWeekDay": 0, "timetables": [{"isHalf": 0, "startDeviceLocation": "150995751", "destDeviceLocation": "150995733", "arriveTime": 1769893993}, {"isHalf": 0, "startDeviceLocation": "150995751", "destDeviceLocation": "150995733", "arriveTime": 1769894547}, {"isHalf": 0, "startDeviceLocation": "150995751", "destDeviceLocation": "150995733", "arriveTime": 1769895087}, {"isHalf": 0, "startDeviceLocation": "150995751", "destDeviceLocation": "150995733", "arriveTime": 1769895567}, {"isHalf": 0, "startDeviceLocation": "150995751", "destDeviceLocation": "150995733", "arriveTime": 1769896047}, {"isHalf": 0, "startDeviceLocation": "150995751", "destDeviceLocation": "150995733", "arriveTime": 1769896527}, {"isHalf": 0, "startDeviceLocation": "150995751", "destDeviceLocation": "150995733", "arriveTime": 1769897007}, {"isHalf": 0, "startDeviceLocation": "150995751", "destDeviceLocation": "150995733", "arriveTime": 1769897487}, {"isHalf": 0, "startDeviceLocation": "150995751", "destDeviceLocation": "150995733", "arriveTime": 1769897967}, {"isHalf": 0, "startDeviceLocation": "150995751", "destDeviceLocation": "150995733", "arriveTime": 1769898447}, {"isHalf": 0, "startDeviceLocation": "150995751", "destDeviceLocation": "150995733", "arriveTime": 1769898927}, {"isHalf": 0, "startDeviceLocation": "150995751", "destDeviceLocation": "150995733", "arriveTime": 1769899407}, {"isHalf": 0, "startDeviceLocation": "150995751", "destDeviceLocation": "150995733", "arriveTime": 1769899887}, {"isHalf": 0, "startDeviceLocation": "150995751", "destDeviceLocation": "150995733", "arriveTime": 1769900367}, {"isHalf": 0, "startDeviceLocation": "150995751", "destDeviceLocation": "150995733", "arriveTime": 1769900847}, {"isHalf": 0, "startDeviceLocation": "150995751", "destDeviceLocation": "150995733", "arriveTime": 1769901327}, {"isHalf": 0, "startDeviceLocation": "150995751", "destDeviceLocation": "150995733", "arriveTime": 1769901807}, {"isHalf": 0, "startDeviceLocation": "150995751", "destDeviceLocation": "150995733", "arriveTime": 1769902167}, {"isHalf": 0, "startDeviceLocation": "150995751", "destDeviceLocation": "150995733", "arriveTime": 1769902467}, {"isHalf": 0, "startDeviceLocation": "150995751", "destDeviceLocation": "150995733", "arriveTime": 1769902787}, {"isHalf": 0, "startDeviceLocation": "150995751", "destDeviceLocation": "150995733", "arriveTime": 1769903122}, {"isHalf": 0, "startDeviceLocation": "150995751", "destDeviceLocation": "150995733", "arriveTime": 1769903367}, {"isHalf": 0, "startDeviceLocation": "150995751", "destDeviceLocation": "150995733", "arriveTime": 1769903667}, {"isHalf": 0, "startDeviceLocation": "150995751", "destDeviceLocation": "150995733", "arriveTime": 1769903967}, {"isHalf": 0, "startDeviceLocation": "150995751", "destDeviceLocation": "150995733", "arriveTime": 1769904267}, {"isHalf": 0, "startDeviceLocation": "150995751", "destDeviceLocation": "150995733", "arriveTime": 1769904567}, {"isHalf": 0, "startDeviceLocation": "150995751", "destDeviceLocation": "150995733", "arriveTime": 1769904867}, {"isHalf": 0, "startDeviceLocation": "150995751", "destDeviceLocation": "150995733", "arriveTime": 1769905167}, {"isHalf": 0, "startDeviceLocation": "150995751", "destDeviceLocation": "150995733", "arriveTime": 1769905467}, {"isHalf": 0, "startDeviceLocation": "150995751", "destDeviceLocation": "150995733", "arriveTime": 1769905767}, {"isHalf": 0, "startDeviceLocation": "150995751", "destDeviceLocation": "150995733", "arriveTime": 1769906067}, {"isHalf": 0, "startDeviceLocation": "150995751", "destDeviceLocation": "150995733", "arriveTime": 1769906367}, {"isHalf": 0, "startDeviceLocation": "150995751", "destDeviceLocation": "150995733", "arriveTime": 1769906667}, {"isHalf": 0, "startDeviceLocation": "150995751", "destDeviceLocation": "150995733", "arriveTime": 1769906967}, {"isHalf": 0, "startDeviceLocation": "150995751", "destDeviceLocation": "150995733", "arriveTime": 1769907267}, {"isHalf": 0, "startDeviceLocation": "150995751", "destDeviceLocation": "150995733", "arriveTime": 1769907567}, {"isHalf": 0, "startDeviceLocation": "150995751", "destDeviceLocation": "150995733", "arriveTime": 1769907867}, {"isHalf": 0, "startDeviceLocation": "150995751", "destDeviceLocation": "150995733", "arriveTime": 1769908167}, {"isHalf": 0, "startDeviceLocation": "150995751", "destDeviceLocation": "150995733", "arriveTime": 1769908467}, {"isHalf": 0, "startDeviceLocation": "150995751", "destDeviceLocation": "150995733", "arriveTime": 1769908767}, {"isHalf": 0, "startDeviceLocation": "150995751", "destDeviceLocation": "150995733", "arriveTime": 1769909067}, {"isHalf": 0, "startDeviceLocation": "150995751", "destDeviceLocation": "150995733", "arriveTime": 1769909367}, {"isHalf": 0, "startDeviceLocation": "150995751", "destDeviceLocation": "150995733", "arriveTime": 1769909667}, {"isHalf": 0, "startDeviceLocation": "150995751", "destDeviceLocation": "150995733", "arriveTime": 1769909967}, {"isHalf": 0, "startDeviceLocation": "150995751", "destDeviceLocation": "150995733", "arriveTime": 1769910267}, {"isHalf": 0, "startDeviceLocation": "150995751", "destDeviceLocation": "150995733", "arriveTime": 1769910567}, {"isHalf": 0, "startDeviceLocation": "150995751", "destDeviceLocation": "150995733", "arriveTime": 1769910867}, {"isHalf": 0, "startDeviceLocation": "150995751", "destDeviceLocation": "150995733", "arriveTime": 1769911167}, {"isHalf": 0, "startDeviceLocation": "150995751", "destDeviceLocation": "150995733", "arriveTime": 1769911467}, {"isHalf": 0, "startDeviceLocation": "150995751", "destDeviceLocation": "150995733", "arriveTime": 1769911767}, {"isHalf": 0, "startDeviceLocation": "150995751", "destDeviceLocation": "150995733", "arriveTime": 1769912067}, {"isHalf": 0, "startDeviceLocation": "150995751", "destDeviceLocation": "150995733", "arriveTime": 1769912367}, {"isHalf": 0, "startDeviceLocation": "150995751", "destDeviceLocation": "150995733", "arriveTime": 1769912667}, {"isHalf": 0, "startDeviceLocation": "150995751", "destDeviceLocation": "150995733", "arriveTime": 1769912967}, {"isHalf": 0, "startDeviceLocation": "150995751", "destDeviceLocation": "150995733", "arriveTime": 1769913267}, {"isHalf": 0, "startDeviceLocation": "150995751", "destDeviceLocation": "150995733", "arriveTime": 1769913567}, {"isHalf": 0, "startDeviceLocation": "150995751", "destDeviceLocation": "150995733", "arriveTime": 1769913867}, {"isHalf": 0, "startDeviceLocation": "150995751", "destDeviceLocation": "150995733", "arriveTime": 1769914111}, {"isHalf": 0, "startDeviceLocation": "150995751", "destDeviceLocation": "150995733", "arriveTime": 1769914531}, {"isHalf": 0, "startDeviceLocation": "150995751", "destDeviceLocation": "150995733", "arriveTime": 1769914951}, {"isHalf": 0, "startDeviceLocation": "150995751", "destDeviceLocation": "150995733", "arriveTime": 1769915371}, {"isHalf": 0, "startDeviceLocation": "150995751", "destDeviceLocation": "150995733", "arriveTime": 1769915791}, {"isHalf": 0, "startDeviceLocation": "150995751", "destDeviceLocation": "150995733", "arriveTime": 1769916211}, {"isHalf": 0, "startDeviceLocation": "150995751", "destDeviceLocation": "150995733", "arriveTime": 1769916631}, {"isHalf": 0, "startDeviceLocation": "150995751", "destDeviceLocation": "150995733", "arriveTime": 1769917051}, {"isHalf": 0, "startDeviceLocation": "150995751", "destDeviceLocation": "150995733", "arriveTime": 1769917471}, {"isHalf": 0, "startDeviceLocation": "150995751", "destDeviceLocation": "150995733", "arriveTime": 1769917891}, {"isHalf": 0, "startDeviceLocation": "150995751", "destDeviceLocation": "150995733", "arriveTime": 1769918336}, {"isHalf": 0, "startDeviceLocation": "150995751", "destDeviceLocation": "150995733", "arriveTime": 1769918731}, {"isHalf": 0, "startDeviceLocation": "150995751", "destDeviceLocation": "150995733", "arriveTime": 1769919151}, {"isHalf": 0, "startDeviceLocation": "150995751", "destDeviceLocation": "150995733", "arriveTime": 1769919571}, {"isHalf": 0, "startDeviceLocation": "150995751", "destDeviceLocation": "150995733", "arriveTime": 1769919991}, {"isHalf": 0, "startDeviceLocation": "150995751", "destDeviceLocation": "150995733", "arriveTime": 1769920411}, {"isHalf": 0, "startDeviceLocation": "150995751", "destDeviceLocation": "150995733", "arriveTime": 1769920831}, {"isHalf": 0, "startDeviceLocation": "150995751", "destDeviceLocation": "150995733", "arriveTime": 1769921251}, {"isHalf": 0, "startDeviceLocation": "150995751", "destDeviceLocation": "150995733", "arriveTime": 1769921671}, {"isHalf": 0, "startDeviceLocation": "150995751", "destDeviceLocation": "150995733", "arriveTime": 1769922116}, {"isHalf": 0, "startDeviceLocation": "150995751", "destDeviceLocation": "150995733", "arriveTime": 1769922511}, {"isHalf": 0, "startDeviceLocation": "150995751", "destDeviceLocation": "150995733", "arriveTime": 1769922931}, {"isHalf": 0, "startDeviceLocation": "150995751", "destDeviceLocation": "150995733", "arriveTime": 1769923351}, {"isHalf": 0, "startDeviceLocation": "150995751", "destDeviceLocation": "150995733", "arriveTime": 1769923771}, {"isHalf": 0, "startDeviceLocation": "150995751", "destDeviceLocation": "150995733", "arriveTime": 1769924191}, {"isHalf": 0, "startDeviceLocation": "150995751", "destDeviceLocation": "150995733", "arriveTime": 1769924611}, {"isHalf": 0, "startDeviceLocation": "150995751", "destDeviceLocation": "150995733", "arriveTime": 1769925031}, {"isHalf": 0, "startDeviceLocation": "150995751", "destDeviceLocation": "150995733", "arriveTime": 1769925451}, {"isHalf": 0, "startDeviceLocation": "150995751", "destDeviceLocation": "150995733", "arriveTime": 1769925896}, {"isHalf": 0, "startDeviceLocation": "150995751", "destDeviceLocation": "150995733", "arriveTime": 1769926291}, {"isHalf": 0, "startDeviceLocation": "150995751", "destDeviceLocation": "150995733", "arriveTime": 1769926711}, {"isHalf": 0, "startDeviceLocation": "150995751", "destDeviceLocation": "150995733", "arriveTime": 1769927131}, {"isHalf": 0, "startDeviceLocation": "150995751", "destDeviceLocation": "150995733", "arriveTime": 1769927551}, {"isHalf": 0, "startDeviceLocation": "150995751", "destDeviceLocation": "150995733", "arriveTime": 1769927971}, {"isHalf": 0, "startDeviceLocation": "150995751", "destDeviceLocation": "150995733", "arriveTime": 1769928391}, {"isHalf": 0, "startDeviceLocation": "150995751", "destDeviceLocation": "150995733", "arriveTime": 1769928811}, {"isHalf": 0, "startDeviceLocation": "150995751", "destDeviceLocation": "150995733", "arriveTime": 1769929231}, {"isHalf": 0, "startDeviceLocation": "150995751", "destDeviceLocation": "150995733", "arriveTime": 1769929676}, {"isHalf": 0, "startDeviceLocation": "150995751", "destDeviceLocation": "150995733", "arriveTime": 1769930071}, {"isHalf": 0, "startDeviceLocation": "150995751", "destDeviceLocation": "150995733", "arriveTime": 1769930491}, {"isHalf": 0, "startDeviceLocation": "150995751", "destDeviceLocation": "150995733", "arriveTime": 1769930911}, {"isHalf": 0, "startDeviceLocation": "150995751", "destDeviceLocation": "150995733", "arriveTime": 1769931331}, {"isHalf": 0, "startDeviceLocation": "150995751", "destDeviceLocation": "150995733", "arriveTime": 1769931751}, {"isHalf": 0, "startDeviceLocation": "150995751", "destDeviceLocation": "150995733", "arriveTime": 1769932171}, {"isHalf": 0, "startDeviceLocation": "150995751", "destDeviceLocation": "150995733", "arriveTime": 1769932591}, {"isHalf": 0, "startDeviceLocation": "150995751", "destDeviceLocation": "150995733", "arriveTime": 1769933011}, {"isHalf": 0, "startDeviceLocation": "150995751", "destDeviceLocation": "150995733", "arriveTime": 1769933456}, {"isHalf": 0, "startDeviceLocation": "150995751", "destDeviceLocation": "150995733", "arriveTime": 1769933851}, {"isHalf": 0, "startDeviceLocation": "150995751", "destDeviceLocation": "150995733", "arriveTime": 1769934271}, {"isHalf": 0, "startDeviceLocation": "150995751", "destDeviceLocation": "150995733", "arriveTime": 1769934631}, {"isHalf": 0, "startDeviceLocation": "150995751", "destDeviceLocation": "150995733", "arriveTime": 1769934991}, {"isHalf": 0, "startDeviceLocation": "150995751", "destDeviceLocation": "150995733", "arriveTime": 1769935291}, {"isHalf": 0, "startDeviceLocation": "150995751", "destDeviceLocation": "150995733", "arriveTime": 1769935591}, {"isHalf": 0, "startDeviceLocation": "150995751", "destDeviceLocation": "150995733", "arriveTime": 1769935921}, {"isHalf": 0, "startDeviceLocation": "150995751", "destDeviceLocation": "150995733", "arriveTime": 1769936251}, {"isHalf": 0, "startDeviceLocation": "150995751", "destDeviceLocation": "150995733", "arriveTime": 1769936491}, {"isHalf": 0, "startDeviceLocation": "150995751", "destDeviceLocation": "150995733", "arriveTime": 1769936791}, {"isHalf": 0, "startDeviceLocation": "150995751", "destDeviceLocation": "150995733", "arriveTime": 1769937116}, {"isHalf": 0, "startDeviceLocation": "150995751", "destDeviceLocation": "150995733", "arriveTime": 1769937391}, {"isHalf": 0, "startDeviceLocation": "150995751", "destDeviceLocation": "150995733", "arriveTime": 1769937691}, {"isHalf": 0, "startDeviceLocation": "150995751", "destDeviceLocation": "150995733", "arriveTime": 1769937991}, {"isHalf": 0, "startDeviceLocation": "150995751", "destDeviceLocation": "150995733", "arriveTime": 1769938291}, {"isHalf": 0, "startDeviceLocation": "150995751", "destDeviceLocation": "150995733", "arriveTime": 1769938591}, {"isHalf": 0, "startDeviceLocation": "150995751", "destDeviceLocation": "150995733", "arriveTime": 1769938891}, {"isHalf": 0, "startDeviceLocation": "150995751", "destDeviceLocation": "150995733", "arriveTime": 1769939191}, {"isHalf": 0, "startDeviceLocation": "150995751", "destDeviceLocation": "150995733", "arriveTime": 1769939491}, {"isHalf": 0, "startDeviceLocation": "150995751", "destDeviceLocation": "150995733", "arriveTime": 1769939791}, {"isHalf": 0, "startDeviceLocation": "150995751", "destDeviceLocation": "150995733", "arriveTime": 1769940091}, {"isHalf": 0, "startDeviceLocation": "150995751", "destDeviceLocation": "150995733", "arriveTime": 1769940391}, {"isHalf": 0, "startDeviceLocation": "150995751", "destDeviceLocation": "150995733", "arriveTime": 1769940691}, {"isHalf": 0, "startDeviceLocation": "150995751", "destDeviceLocation": "150995733", "arriveTime": 1769941016}, {"isHalf": 0, "startDeviceLocation": "150995751", "destDeviceLocation": "150995733", "arriveTime": 1769941291}, {"isHalf": 0, "startDeviceLocation": "150995751", "destDeviceLocation": "150995733", "arriveTime": 1769941591}, {"isHalf": 0, "startDeviceLocation": "150995751", "destDeviceLocation": "150995733", "arriveTime": 1769941891}, {"isHalf": 0, "startDeviceLocation": "150995751", "destDeviceLocation": "150995733", "arriveTime": 1769942191}, {"isHalf": 0, "startDeviceLocation": "150995751", "destDeviceLocation": "150995733", "arriveTime": 1769942491}, {"isHalf": 0, "startDeviceLocation": "150995751", "destDeviceLocation": "150995733", "arriveTime": 1769942791}, {"isHalf": 0, "startDeviceLocation": "150995751", "destDeviceLocation": "150995733", "arriveTime": 1769943091}, {"isHalf": 0, "startDeviceLocation": "150995751", "destDeviceLocation": "150995733", "arriveTime": 1769943391}, {"isHalf": 0, "startDeviceLocation": "150995751", "destDeviceLocation": "150995733", "arriveTime": 1769943691}, {"isHalf": 0, "startDeviceLocation": "150995751", "destDeviceLocation": "150995733", "arriveTime": 1769943991}, {"isHalf": 0, "startDeviceLocation": "150995751", "destDeviceLocation": "150995733", "arriveTime": 1769944291}, {"isHalf": 0, "startDeviceLocation": "150995751", "destDeviceLocation": "150995733", "arriveTime": 1769944591}, {"isHalf": 0, "startDeviceLocation": "150995751", "destDeviceLocation": "150995733", "arriveTime": 1769944916}, {"isHalf": 0, "startDeviceLocation": "150995751", "destDeviceLocation": "150995733", "arriveTime": 1769945191}, {"isHalf": 0, "startDeviceLocation": "150995751", "destDeviceLocation": "150995733", "arriveTime": 1769945551}, {"isHalf": 0, "startDeviceLocation": "150995751", "destDeviceLocation": "150995733", "arriveTime": 1769945911}, {"isHalf": 0, "startDeviceLocation": "150995751", "destDeviceLocation": "150995733", "arriveTime": 1769946275}, {"isHalf": 0, "startDeviceLocation": "150995751", "destDeviceLocation": "150995733", "arriveTime": 1769946635}, {"isHalf": 0, "startDeviceLocation": "150995751", "destDeviceLocation": "150995733", "arriveTime": 1769947055}, {"isHalf": 0, "startDeviceLocation": "150995751", "destDeviceLocation": "150995733", "arriveTime": 1769947475}, {"isHalf": 0, "startDeviceLocation": "150995751", "destDeviceLocation": "150995733", "arriveTime": 1769947895}, {"isHalf": 0, "startDeviceLocation": "150995751", "destDeviceLocation": "150995733", "arriveTime": 1769948315}, {"isHalf": 0, "startDeviceLocation": "150995751", "destDeviceLocation": "150995733", "arriveTime": 1769948760}, {"isHalf": 0, "startDeviceLocation": "150995751", "destDeviceLocation": "150995733", "arriveTime": 1769949155}, {"isHalf": 0, "startDeviceLocation": "150995751", "destDeviceLocation": "150995733", "arriveTime": 1769949575}, {"isHalf": 0, "startDeviceLocation": "150995751", "destDeviceLocation": "150995733", "arriveTime": 1769949995}, {"isHalf": 0, "startDeviceLocation": "150995751", "destDeviceLocation": "150995733", "arriveTime": 1769950415}, {"isHalf": 0, "startDeviceLocation": "150995751", "destDeviceLocation": "150995733", "arriveTime": 1769950835}, {"isHalf": 0, "startDeviceLocation": "150995751", "destDeviceLocation": "150995733", "arriveTime": 1769951255}, {"isHalf": 0, "startDeviceLocation": "150995751", "destDeviceLocation": "150995733", "arriveTime": 1769951675}, {"isHalf": 0, "startDeviceLocation": "150995751", "destDeviceLocation": "150995733", "arriveTime": 1769952095}, {"isHalf": 0, "startDeviceLocation": "150995751", "destDeviceLocation": "150995733", "arriveTime": 1769952540}, {"isHalf": 0, "startDeviceLocation": "150995751", "destDeviceLocation": "150995733", "arriveTime": 1769952935}, {"isHalf": 0, "startDeviceLocation": "150995751", "destDeviceLocation": "150995733", "arriveTime": 1769953355}, {"isHalf": 0, "startDeviceLocation": "150995751", "destDeviceLocation": "150995733", "arriveTime": 1769953775}, {"isHalf": 0, "startDeviceLocation": "150995751", "destDeviceLocation": "150995733", "arriveTime": 1769954195}, {"isHalf": 0, "startDeviceLocation": "150995751", "destDeviceLocation": "150995733", "arriveTime": 1769954615}, {"isHalf": 0, "startDeviceLocation": "150995751", "destDeviceLocation": "150995733", "arriveTime": 1769955035}, {"isHalf": 0, "startDeviceLocation": "150995751", "destDeviceLocation": "150995733", "arriveTime": 1769955455}, {"isHalf": 0, "startDeviceLocation": "150995751", "destDeviceLocation": "150995733", "arriveTime": 1769955875}, {"isHalf": 0, "startDeviceLocation": "150995751", "destDeviceLocation": "150995733", "arriveTime": 1769956320}, {"isHalf": 0, "startDeviceLocation": "150995751", "destDeviceLocation": "150995733", "arriveTime": 1769956715}, {"isHalf": 0, "startDeviceLocation": "150995751", "destDeviceLocation": "150995733", "arriveTime": 1769957105}, {"isHalf": 0, "startDeviceLocation": "150995751", "destDeviceLocation": "150995733", "arriveTime": 1769957511}, {"isHalf": 0, "startDeviceLocation": "150995751", "destDeviceLocation": "150995733", "arriveTime": 1769957893}]}, {"isWeekDay": 1, "timetables": [{"isHalf": 0, "startDeviceLocation": "150995751", "destDeviceLocation": "150995733", "arriveTime": 1770239593}, {"isHalf": 0, "startDeviceLocation": "150995751", "destDeviceLocation": "150995733", "arriveTime": 1770240147}, {"isHalf": 0, "startDeviceLocation": "150995751", "destDeviceLocation": "150995733", "arriveTime": 1770240687}, {"isHalf": 0, "startDeviceLocation": "150995751", "destDeviceLocation": "150995733", "arriveTime": 1770241167}, {"isHalf": 0, "startDeviceLocation": "150995751", "destDeviceLocation": "150995733", "arriveTime": 1770241647}, {"isHalf": 0, "startDeviceLocation": "150995751", "destDeviceLocation": "150995733", "arriveTime": 1770242127}, {"isHalf": 0, "startDeviceLocation": "150995751", "destDeviceLocation": "150995733", "arriveTime": 1770242607}, {"isHalf": 0, "startDeviceLocation": "150995751", "destDeviceLocation": "150995733", "arriveTime": 1770243087}, {"isHalf": 0, "startDeviceLocation": "150995751", "destDeviceLocation": "150995733", "arriveTime": 1770243567}, {"isHalf": 0, "startDeviceLocation": "150995751", "destDeviceLocation": "150995733", "arriveTime": 1770243987}, {"isHalf": 0, "startDeviceLocation": "150995751", "destDeviceLocation": "150995733", "arriveTime": 1770244402}, {"isHalf": 0, "startDeviceLocation": "150995751", "destDeviceLocation": "150995733", "arriveTime": 1770244647}, {"isHalf": 0, "startDeviceLocation": "150995751", "destDeviceLocation": "150995733", "arriveTime": 1770244947}, {"isHalf": 0, "startDeviceLocation": "150995751", "destDeviceLocation": "150995733", "arriveTime": 1770245187}, {"isHalf": 0, "startDeviceLocation": "150995751", "destDeviceLocation": "150995733", "arriveTime": 1770245427}, {"isHalf": 0, "startDeviceLocation": "150995751", "destDeviceLocation": "150995733", "arriveTime": 1770245667}, {"isHalf": 0, "startDeviceLocation": "150995751", "destDeviceLocation": "150995733", "arriveTime": 1770245907}, {"isHalf": 0, "startDeviceLocation": "150995751", "destDeviceLocation": "150995733", "arriveTime": 1770246147}, {"isHalf": 0, "startDeviceLocation": "150995751", "destDeviceLocation": "150995733", "arriveTime": 1770246387}, {"isHalf": 0, "startDeviceLocation": "150995751", "destDeviceLocation": "150995733", "arriveTime": 1770246627}, {"isHalf": 0, "startDeviceLocation": "150995751", "destDeviceLocation": "150995733", "arriveTime": 1770246867}, {"isHalf": 0, "startDeviceLocation": "150995751", "destDeviceLocation": "150995733", "arriveTime": 1770247107}, {"isHalf": 0, "startDeviceLocation": "150995751", "destDeviceLocation": "150995733", "arriveTime": 1770247347}, {"isHalf": 0, "startDeviceLocation": "150995751", "destDeviceLocation": "150995733", "arriveTime": 1770247587}, {"isHalf": 0, "startDeviceLocation": "150995751", "destDeviceLocation": "150995733", "arriveTime": 1770247827}, {"isHalf": 0, "startDeviceLocation": "150995751", "destDeviceLocation": "150995733", "arriveTime": 1770248067}, {"isHalf": 0, "startDeviceLocation": "150995751", "destDeviceLocation": "150995733", "arriveTime": 1770248307}, {"isHalf": 0, "startDeviceLocation": "150995751", "destDeviceLocation": "150995733", "arriveTime": 1770248547}, {"isHalf": 0, "startDeviceLocation": "150995751", "destDeviceLocation": "150995733", "arriveTime": 1770248787}, {"isHalf": 0, "startDeviceLocation": "150995751", "destDeviceLocation": "150995733", "arriveTime": 1770249027}, {"isHalf": 0, "startDeviceLocation": "150995751", "destDeviceLocation": "150995733", "arriveTime": 1770249267}, {"isHalf": 0, "startDeviceLocation": "150995751", "destDeviceLocation": "150995733", "arriveTime": 1770249507}, {"isHalf": 0, "startDeviceLocation": "150995751", "destDeviceLocation": "150995733", "arriveTime": 1770249747}, {"isHalf": 0, "startDeviceLocation": "150995751", "destDeviceLocation": "150995733", "arriveTime": 1770249987}, {"isHalf": 0, "startDeviceLocation": "150995751", "destDeviceLocation": "150995733", "arriveTime": 1770250227}, {"isHalf": 0, "startDeviceLocation": "150995751", "destDeviceLocation": "150995733", "arriveTime": 1770250467}, {"isHalf": 0, "startDeviceLocation": "150995751", "destDeviceLocation": "150995733", "arriveTime": 1770250707}, {"isHalf": 0, "startDeviceLocation": "150995751", "destDeviceLocation": "150995733", "arriveTime": 1770250947}, {"isHalf": 0, "startDeviceLocation": "150995751", "destDeviceLocation": "150995733", "arriveTime": 1770251187}, {"isHalf": 0, "startDeviceLocation": "150995751", "destDeviceLocation": "150995733", "arriveTime": 1770251427}, {"isHalf": 0, "startDeviceLocation": "150995751", "destDeviceLocation": "150995733", "arriveTime": 1770251667}, {"isHalf": 0, "startDeviceLocation": "150995751", "destDeviceLocation": "150995733", "arriveTime": 1770251907}, {"isHalf": 0, "startDeviceLocation": "150995751", "destDeviceLocation": "150995733", "arriveTime": 1770252147}, {"isHalf": 0, "startDeviceLocation": "150995751", "destDeviceLocation": "150995733", "arriveTime": 1770252387}, {"isHalf": 0, "startDeviceLocation": "150995751", "destDeviceLocation": "150995733", "arriveTime": 1770252627}, {"isHalf": 0, "startDeviceLocation": "150995751", "destDeviceLocation": "150995733", "arriveTime": 1770252927}, {"isHalf": 0, "startDeviceLocation": "150995751", "destDeviceLocation": "150995733", "arriveTime": 1770253227}, {"isHalf": 0, "startDeviceLocation": "150995751", "destDeviceLocation": "150995733", "arriveTime": 1770253587}, {"isHalf": 0, "startDeviceLocation": "150995751", "destDeviceLocation": "150995733", "arriveTime": 1770253947}, {"isHalf": 0, "startDeviceLocation": "150995751", "destDeviceLocation": "150995733", "arriveTime": 1770254367}, {"isHalf": 0, "startDeviceLocation": "150995751", "destDeviceLocation": "150995733", "arriveTime": 1770254787}, {"isHalf": 0, "startDeviceLocation": "150995751", "destDeviceLocation": "150995733", "arriveTime": 1770255207}, {"isHalf": 0, "startDeviceLocation": "150995751", "destDeviceLocation": "150995733", "arriveTime": 1770255627}, {"isHalf": 0, "startDeviceLocation": "150995751", "destDeviceLocation": "150995733", "arriveTime": 1770256047}, {"isHalf": 0, "startDeviceLocation": "150995751", "destDeviceLocation": "150995733", "arriveTime": 1770256467}, {"isHalf": 0, "startDeviceLocation": "150995751", "destDeviceLocation": "150995733", "arriveTime": 1770256887}, {"isHalf": 0, "startDeviceLocation": "150995751", "destDeviceLocation": "150995733", "arriveTime": 1770257307}, {"isHalf": 0, "startDeviceLocation": "150995751", "destDeviceLocation": "150995733", "arriveTime": 1770257727}, {"isHalf": 0, "startDeviceLocation": "150995751", "destDeviceLocation": "150995733", "arriveTime": 1770258147}, {"isHalf": 0, "startDeviceLocation": "150995751", "destDeviceLocation": "150995733", "arriveTime": 1770258567}, {"isHalf": 0, "startDeviceLocation": "150995751", "destDeviceLocation": "150995733", "arriveTime": 1770258987}, {"isHalf": 0, "startDeviceLocation": "150995751", "destDeviceLocation": "150995733", "arriveTime": 1770259407}, {"isHalf": 0, "startDeviceLocation": "150995751", "destDeviceLocation": "150995733", "arriveTime": 1770259827}, {"isHalf": 0, "startDeviceLocation": "150995751", "destDeviceLocation": "150995733", "arriveTime": 1770260247}, {"isHalf": 0, "startDeviceLocation": "150995751", "destDeviceLocation": "150995733", "arriveTime": 1770260667}, {"isHalf": 0, "startDeviceLocation": "150995751", "destDeviceLocation": "150995733", "arriveTime": 1770261087}, {"isHalf": 0, "startDeviceLocation": "150995751", "destDeviceLocation": "150995733", "arriveTime": 1770261507}, {"isHalf": 0, "startDeviceLocation": "150995751", "destDeviceLocation": "150995733", "arriveTime": 1770261927}, {"isHalf": 0, "startDeviceLocation": "150995751", "destDeviceLocation": "150995733", "arriveTime": 1770262347}, {"isHalf": 0, "startDeviceLocation": "150995751", "destDeviceLocation": "150995733", "arriveTime": 1770262767}, {"isHalf": 0, "startDeviceLocation": "150995751", "destDeviceLocation": "150995733", "arriveTime": 1770263187}, {"isHalf": 0, "startDeviceLocation": "150995751", "destDeviceLocation": "150995733", "arriveTime": 1770263607}, {"isHalf": 0, "startDeviceLocation": "150995751", "destDeviceLocation": "150995733", "arriveTime": 1770264027}, {"isHalf": 0, "startDeviceLocation": "150995751", "destDeviceLocation": "150995733", "arriveTime": 1770264447}, {"isHalf": 0, "startDeviceLocation": "150995751", "destDeviceLocation": "150995733", "arriveTime": 1770264867}, {"isHalf": 0, "startDeviceLocation": "150995751", "destDeviceLocation": "150995733", "arriveTime": 1770265287}, {"isHalf": 0, "startDeviceLocation": "150995751", "destDeviceLocation": "150995733", "arriveTime": 1770265707}, {"isHalf": 0, "startDeviceLocation": "150995751", "destDeviceLocation": "150995733", "arriveTime": 1770266127}, {"isHalf": 0, "startDeviceLocation": "150995751", "destDeviceLocation": "150995733", "arriveTime": 1770266547}, {"isHalf": 0, "startDeviceLocation": "150995751", "destDeviceLocation": "150995733", "arriveTime": 1770266967}, {"isHalf": 0, "startDeviceLocation": "150995751", "destDeviceLocation": "150995733", "arriveTime": 1770267387}, {"isHalf": 0, "startDeviceLocation": "150995751", "destDeviceLocation": "150995733", "arriveTime": 1770267807}, {"isHalf": 0, "startDeviceLocation": "150995751", "destDeviceLocation": "150995733", "arriveTime": 1770268227}, {"isHalf": 0, "startDeviceLocation": "150995751", "destDeviceLocation": "150995733", "arriveTime": 1770268647}, {"isHalf": 0, "startDeviceLocation": "150995751", "destDeviceLocation": "150995733", "arriveTime": 1770269067}, {"isHalf": 0, "startDeviceLocation": "150995751", "destDeviceLocation": "150995733", "arriveTime": 1770269487}, {"isHalf": 0, "startDeviceLocation": "150995751", "destDeviceLocation": "150995733", "arriveTime": 1770269907}, {"isHalf": 0, "startDeviceLocation": "150995751", "destDeviceLocation": "150995733", "arriveTime": 1770270327}, {"isHalf": 0, "startDeviceLocation": "150995751", "destDeviceLocation": "150995733", "arriveTime": 1770270747}, {"isHalf": 0, "startDeviceLocation": "150995751", "destDeviceLocation": "150995733", "arriveTime": 1770271167}, {"isHalf": 0, "startDeviceLocation": "150995751", "destDeviceLocation": "150995733", "arriveTime": 1770271587}, {"isHalf": 0, "startDeviceLocation": "150995751", "destDeviceLocation": "150995733", "arriveTime": 1770272007}, {"isHalf": 0, "startDeviceLocation": "150995751", "destDeviceLocation": "150995733", "arriveTime": 1770272427}, {"isHalf": 0, "startDeviceLocation": "150995751", "destDeviceLocation": "150995733", "arriveTime": 1770272847}, {"isHalf": 0, "startDeviceLocation": "150995751", "destDeviceLocation": "150995733", "arriveTime": 1770273267}, {"isHalf": 0, "startDeviceLocation": "150995751", "destDeviceLocation": "150995733", "arriveTime": 1770273687}, {"isHalf": 0, "startDeviceLocation": "150995751", "destDeviceLocation": "150995733", "arriveTime": 1770274107}, {"isHalf": 0, "startDeviceLocation": "150995751", "destDeviceLocation": "150995733", "arriveTime": 1770274527}, {"isHalf": 0, "startDeviceLocation": "150995751", "destDeviceLocation": "150995733", "arriveTime": 1770274947}, {"isHalf": 0, "startDeviceLocation": "150995751", "destDeviceLocation": "150995733", "arriveTime": 1770275367}, {"isHalf": 0, "startDeviceLocation": "150995751", "destDeviceLocation": "150995733", "arriveTime": 1770275787}, {"isHalf": 0, "startDeviceLocation": "150995751", "destDeviceLocation": "150995733", "arriveTime": 1770276207}, {"isHalf": 0, "startDeviceLocation": "150995751", "destDeviceLocation": "150995733", "arriveTime": 1770276627}, {"isHalf": 0, "startDeviceLocation": "150995751", "destDeviceLocation": "150995733", "arriveTime": 1770277047}, {"isHalf": 0, "startDeviceLocation": "150995751", "destDeviceLocation": "150995733", "arriveTime": 1770277467}, {"isHalf": 0, "startDeviceLocation": "150995751", "destDeviceLocation": "150995733", "arriveTime": 1770277887}, {"isHalf": 0, "startDeviceLocation": "150995751", "destDeviceLocation": "150995733", "arriveTime": 1770278307}, {"isHalf": 0, "startDeviceLocation": "150995751", "destDeviceLocation": "150995733", "arriveTime": 1770278727}, {"isHalf": 0, "startDeviceLocation": "150995751", "destDeviceLocation": "150995733", "arriveTime": 1770279147}, {"isHalf": 0, "startDeviceLocation": "150995751", "destDeviceLocation": "150995733", "arriveTime": 1770279567}, {"isHalf": 0, "startDeviceLocation": "150995751", "destDeviceLocation": "150995733", "arriveTime": 1770279987}, {"isHalf": 0, "startDeviceLocation": "150995751", "destDeviceLocation": "150995733", "arriveTime": 1770280407}, {"isHalf": 0, "startDeviceLocation": "150995751", "destDeviceLocation": "150995733", "arriveTime": 1770280707}, {"isHalf": 0, "startDeviceLocation": "150995751", "destDeviceLocation": "150995733", "arriveTime": 1770281007}, {"isHalf": 0, "startDeviceLocation": "150995751", "destDeviceLocation": "150995733", "arriveTime": 1770281307}, {"isHalf": 0, "startDeviceLocation": "150995751", "destDeviceLocation": "150995733", "arriveTime": 1770281547}, {"isHalf": 0, "startDeviceLocation": "150995751", "destDeviceLocation": "150995733", "arriveTime": 1770281787}, {"isHalf": 0, "startDeviceLocation": "150995751", "destDeviceLocation": "150995733", "arriveTime": 1770282027}, {"isHalf": 0, "startDeviceLocation": "150995751", "destDeviceLocation": "150995733", "arriveTime": 1770282267}, {"isHalf": 0, "startDeviceLocation": "150995751", "destDeviceLocation": "150995733", "arriveTime": 1770282507}, {"isHalf": 0, "startDeviceLocation": "150995751", "destDeviceLocation": "150995733", "arriveTime": 1770282747}, {"isHalf": 0, "startDeviceLocation": "150995751", "destDeviceLocation": "150995733", "arriveTime": 1770282987}, {"isHalf": 0, "startDeviceLocation": "150995751", "destDeviceLocation": "150995733", "arriveTime": 1770283227}, {"isHalf": 0, "startDeviceLocation": "150995751", "destDeviceLocation": "150995733", "arriveTime": 1770283467}, {"isHalf": 0, "startDeviceLocation": "150995751", "destDeviceLocation": "150995733", "arriveTime": 1770283707}, {"isHalf": 0, "startDeviceLocation": "150995751", "destDeviceLocation": "150995733", "arriveTime": 1770283947}, {"isHalf": 0, "startDeviceLocation": "150995751", "destDeviceLocation": "150995733", "arriveTime": 1770284187}, {"isHalf": 0, "startDeviceLocation": "150995751", "destDeviceLocation": "150995733", "arriveTime": 1770284427}, {"isHalf": 0, "startDeviceLocation": "150995751", "destDeviceLocation": "150995733", "arriveTime": 1770284667}, {"isHalf": 0, "startDeviceLocation": "150995751", "destDeviceLocation": "150995733", "arriveTime": 1770284907}, {"isHalf": 0, "startDeviceLocation": "150995751", "destDeviceLocation": "150995733", "arriveTime": 1770285147}, {"isHalf": 0, "startDeviceLocation": "150995751", "destDeviceLocation": "150995733", "arriveTime": 1770285387}, {"isHalf": 0, "startDeviceLocation": "150995751", "destDeviceLocation": "150995733", "arriveTime": 1770285627}, {"isHalf": 0, "startDeviceLocation": "150995751", "destDeviceLocation": "150995733", "arriveTime": 1770285867}, {"isHalf": 0, "startDeviceLocation": "150995751", "destDeviceLocation": "150995733", "arriveTime": 1770286107}, {"isHalf": 0, "startDeviceLocation": "150995751", "destDeviceLocation": "150995733", "arriveTime": 1770286347}, {"isHalf": 0, "startDeviceLocation": "150995751", "destDeviceLocation": "150995733", "arriveTime": 1770286587}, {"isHalf": 0, "startDeviceLocation": "150995751", "destDeviceLocation": "150995733", "arriveTime": 1770286827}, {"isHalf": 0, "startDeviceLocation": "150995751", "destDeviceLocation": "150995733", "arriveTime": 1770287067}, {"isHalf": 0, "startDeviceLocation": "150995751", "destDeviceLocation": "150995733", "arriveTime": 1770287307}, {"isHalf": 0, "startDeviceLocation": "150995751", "destDeviceLocation": "150995733", "arriveTime": 1770287547}, {"isHalf": 0, "startDeviceLocation": "150995751", "destDeviceLocation": "150995733", "arriveTime": 1770287787}, {"isHalf": 0, "startDeviceLocation": "150995751", "destDeviceLocation": "150995733", "arriveTime": 1770288027}, {"isHalf": 0, "startDeviceLocation": "150995751", "destDeviceLocation": "150995733", "arriveTime": 1770288267}, {"isHalf": 0, "startDeviceLocation": "150995751", "destDeviceLocation": "150995733", "arriveTime": 1770288507}, {"isHalf": 0, "startDeviceLocation": "150995751", "destDeviceLocation": "150995733", "arriveTime": 1770288747}, {"isHalf": 0, "startDeviceLocation": "150995751", "destDeviceLocation": "150995733", "arriveTime": 1770288987}, {"isHalf": 0, "startDeviceLocation": "150995751", "destDeviceLocation": "150995733", "arriveTime": 1770289227}, {"isHalf": 0, "startDeviceLocation": "150995751", "destDeviceLocation": "150995733", "arriveTime": 1770289467}, {"isHalf": 0, "startDeviceLocation": "150995751", "destDeviceLocation": "150995733", "arriveTime": 1770289707}, {"isHalf": 0, "startDeviceLocation": "150995751", "destDeviceLocation": "150995733", "arriveTime": 1770289947}, {"isHalf": 0, "startDeviceLocation": "150995751", "destDeviceLocation": "150995733", "arriveTime": 1770290187}, {"isHalf": 0, "startDeviceLocation": "150995751", "destDeviceLocation": "150995733", "arriveTime": 1770290427}, {"isHalf": 0, "startDeviceLocation": "150995751", "destDeviceLocation": "150995733", "arriveTime": 1770290727}, {"isHalf": 0, "startDeviceLocation": "150995751", "destDeviceLocation": "150995733", "arriveTime": 1770291027}, {"isHalf": 0, "startDeviceLocation": "150995751", "destDeviceLocation": "150995733", "arriveTime": 1770291387}, {"isHalf": 0, "startDeviceLocation": "150995751", "destDeviceLocation": "150995733", "arriveTime": 1770291717}, {"isHalf": 0, "startDeviceLocation": "150995751", "destDeviceLocation": "150995733", "arriveTime": 1770292047}, {"isHalf": 0, "startDeviceLocation": "150995751", "destDeviceLocation": "150995733", "arriveTime": 1770292377}, {"isHalf": 0, "startDeviceLocation": "150995751", "destDeviceLocation": "150995733", "arriveTime": 1770292707}, {"isHalf": 0, "startDeviceLocation": "150995751", "destDeviceLocation": "150995733", "arriveTime": 1770293067}, {"isHalf": 0, "startDeviceLocation": "150995751", "destDeviceLocation": "150995733", "arriveTime": 1770293427}, {"isHalf": 0, "startDeviceLocation": "150995751", "destDeviceLocation": "150995733", "arriveTime": 1770293847}, {"isHalf": 0, "startDeviceLocation": "150995751", "destDeviceLocation": "150995733", "arriveTime": 1770294267}, {"isHalf": 0, "startDeviceLocation": "150995751", "destDeviceLocation": "150995733", "arriveTime": 1770294687}, {"isHalf": 0, "startDeviceLocation": "150995751", "destDeviceLocation": "150995733", "arriveTime": 1770295107}, {"isHalf": 0, "startDeviceLocation": "150995751", "destDeviceLocation": "150995733", "arriveTime": 1770295527}, {"isHalf": 0, "startDeviceLocation": "150995751", "destDeviceLocation": "150995733", "arriveTime": 1770295947}, {"isHalf": 0, "startDeviceLocation": "150995751", "destDeviceLocation": "150995733", "arriveTime": 1770296367}, {"isHalf": 0, "startDeviceLocation": "150995751", "destDeviceLocation": "150995733", "arriveTime": 1770296787}, {"isHalf": 0, "startDeviceLocation": "150995751", "destDeviceLocation": "150995733", "arriveTime": 1770297207}, {"isHalf": 0, "startDeviceLocation": "150995751", "destDeviceLocation": "150995733", "arriveTime": 1770297627}, {"isHalf": 0, "startDeviceLocation": "150995751", "destDeviceLocation": "150995733", "arriveTime": 1770298047}, {"isHalf": 0, "startDeviceLocation": "150995751", "destDeviceLocation": "150995733", "arriveTime": 1770298467}, {"isHalf": 0, "startDeviceLocation": "150995751", "destDeviceLocation": "150995733", "arriveTime": 1770298887}, {"isHalf": 0, "startDeviceLocation": "150995751", "destDeviceLocation": "150995733", "arriveTime": 1770299307}, {"isHalf": 0, "startDeviceLocation": "150995751", "destDeviceLocation": "150995733", "arriveTime": 1770299727}, {"isHalf": 0, "startDeviceLocation": "150995751", "destDeviceLocation": "150995733", "arriveTime": 1770300147}, {"isHalf": 0, "startDeviceLocation": "150995751", "destDeviceLocation": "150995733", "arriveTime": 1770300567}, {"isHalf": 0, "startDeviceLocation": "150995751", "destDeviceLocation": "150995733", "arriveTime": 1770300987}, {"isHalf": 0, "startDeviceLocation": "150995751", "destDeviceLocation": "150995733", "arriveTime": 1770301407}, {"isHalf": 0, "startDeviceLocation": "150995751", "destDeviceLocation": "150995733", "arriveTime": 1770301827}, {"isHalf": 0, "startDeviceLocation": "150995751", "destDeviceLocation": "150995733", "arriveTime": 1770302247}, {"isHalf": 0, "startDeviceLocation": "150995751", "destDeviceLocation": "150995733", "arriveTime": 1770302667}, {"isHalf": 0, "startDeviceLocation": "150995751", "destDeviceLocation": "150995733", "arriveTime": 1770303087}, {"isHalf": 0, "startDeviceLocation": "150995751", "destDeviceLocation": "150995733", "arriveTime": 1770303493}]}]}, {"directDeviceLocation": "150995751", "direction": [{"isWeekDay": 0, "timetables": [{"isHalf": 0, "startDeviceLocation": "150995733", "destDeviceLocation": "150995751", "arriveTime": 1769896291}, {"isHalf": 0, "startDeviceLocation": "150995733", "destDeviceLocation": "150995751", "arriveTime": 1769896836}, {"isHalf": 0, "startDeviceLocation": "150995733", "destDeviceLocation": "150995751", "arriveTime": 1769897321}, {"isHalf": 0, "startDeviceLocation": "150995733", "destDeviceLocation": "150995751", "arriveTime": 1769897801}, {"isHalf": 0, "startDeviceLocation": "150995733", "destDeviceLocation": "150995751", "arriveTime": 1769898281}, {"isHalf": 0, "startDeviceLocation": "150995733", "destDeviceLocation": "150995751", "arriveTime": 1769898761}, {"isHalf": 0, "startDeviceLocation": "150995733", "destDeviceLocation": "150995751", "arriveTime": 1769899241}, {"isHalf": 0, "startDeviceLocation": "150995733", "destDeviceLocation": "150995751", "arriveTime": 1769899721}, {"isHalf": 0, "startDeviceLocation": "150995733", "destDeviceLocation": "150995751", "arriveTime": 1769900201}, {"isHalf": 0, "startDeviceLocation": "150995733", "destDeviceLocation": "150995751", "arriveTime": 1769900681}, {"isHalf": 0, "startDeviceLocation": "150995733", "destDeviceLocation": "150995751", "arriveTime": 1769901161}, {"isHalf": 0, "startDeviceLocation": "150995733", "destDeviceLocation": "150995751", "arriveTime": 1769901641}, {"isHalf": 0, "startDeviceLocation": "150995733", "destDeviceLocation": "150995751", "arriveTime": 1769902121}, {"isHalf": 0, "startDeviceLocation": "150995733", "destDeviceLocation": "150995751", "arriveTime": 1769902601}, {"isHalf": 0, "startDeviceLocation": "150995733", "destDeviceLocation": "150995751", "arriveTime": 1769903081}, {"isHalf": 0, "startDeviceLocation": "150995733", "destDeviceLocation": "150995751", "arriveTime": 1769903561}, {"isHalf": 0, "startDeviceLocation": "150995733", "destDeviceLocation": "150995751", "arriveTime": 1769903986}, {"isHalf": 0, "startDeviceLocation": "150995733", "destDeviceLocation": "150995751", "arriveTime": 1769904406}, {"isHalf": 0, "startDeviceLocation": "150995733", "destDeviceLocation": "150995751", "arriveTime": 1769904766}, {"isHalf": 0, "startDeviceLocation": "150995733", "destDeviceLocation": "150995751", "arriveTime": 1769905066}, {"isHalf": 0, "startDeviceLocation": "150995733", "destDeviceLocation": "150995751", "arriveTime": 1769905366}, {"isHalf": 0, "startDeviceLocation": "150995733", "destDeviceLocation": "150995751", "arriveTime": 1769905666}, {"isHalf": 0, "startDeviceLocation": "150995733", "destDeviceLocation": "150995751", "arriveTime": 1769905966}, {"isHalf": 0, "startDeviceLocation": "150995733", "destDeviceLocation": "150995751", "arriveTime": 1769906266}, {"isHalf": 0, "startDeviceLocation": "150995733", "destDeviceLocation": "150995751", "arriveTime": 1769906566}, {"isHalf": 0, "startDeviceLocation": "150995733", "destDeviceLocation": "150995751", "arriveTime": 1769906866}, {"isHalf": 0, "startDeviceLocation": "150995733", "destDeviceLocation": "150995751", "arriveTime": 1769907166}, {"isHalf": 0, "startDeviceLocation": "150995733", "destDeviceLocation": "150995751", "arriveTime": 1769907466}, {"isHalf": 0, "startDeviceLocation": "150995733", "destDeviceLocation": "150995751", "arriveTime": 1769907766}, {"isHalf": 0, "startDeviceLocation": "150995733", "destDeviceLocation": "150995751", "arriveTime": 1769908066}, {"isHalf": 0, "startDeviceLocation": "150995733", "destDeviceLocation": "150995751", "arriveTime": 1769908366}, {"isHalf": 0, "startDeviceLocation": "150995733", "destDeviceLocation": "150995751", "arriveTime": 1769908666}, {"isHalf": 0, "startDeviceLocation": "150995733", "destDeviceLocation": "150995751", "arriveTime": 1769908966}, {"isHalf": 0, "startDeviceLocation": "150995733", "destDeviceLocation": "150995751", "arriveTime": 1769909266}, {"isHalf": 0, "startDeviceLocation": "150995733", "destDeviceLocation": "150995751", "arriveTime": 1769909566}, {"isHalf": 0, "startDeviceLocation": "150995733", "destDeviceLocation": "150995751", "arriveTime": 1769909866}, {"isHalf": 0, "startDeviceLocation": "150995733", "destDeviceLocation": "150995751", "arriveTime": 1769910166}, {"isHalf": 0, "startDeviceLocation": "150995733", "destDeviceLocation": "150995751", "arriveTime": 1769910466}, {"isHalf": 0, "startDeviceLocation": "150995733", "destDeviceLocation": "150995751", "arriveTime": 1769910766}, {"isHalf": 0, "startDeviceLocation": "150995733", "destDeviceLocation": "150995751", "arriveTime": 1769911066}, {"isHalf": 0, "startDeviceLocation": "150995733", "destDeviceLocation": "150995751", "arriveTime": 1769911366}, {"isHalf": 0, "startDeviceLocation": "150995733", "destDeviceLocation": "150995751", "arriveTime": 1769911666}, {"isHalf": 0, "startDeviceLocation": "150995733", "destDeviceLocation": "150995751", "arriveTime": 1769911966}, {"isHalf": 0, "startDeviceLocation": "150995733", "destDeviceLocation": "150995751", "arriveTime": 1769912266}, {"isHalf": 0, "startDeviceLocation": "150995733", "destDeviceLocation": "150995751", "arriveTime": 1769912566}, {"isHalf": 0, "startDeviceLocation": "150995733", "destDeviceLocation": "150995751", "arriveTime": 1769912866}, {"isHalf": 0, "startDeviceLocation": "150995733", "destDeviceLocation": "150995751", "arriveTime": 1769913166}, {"isHalf": 0, "startDeviceLocation": "150995733", "destDeviceLocation": "150995751", "arriveTime": 1769913466}, {"isHalf": 0, "startDeviceLocation": "150995733", "destDeviceLocation": "150995751", "arriveTime": 1769913766}, {"isHalf": 0, "startDeviceLocation": "150995733", "destDeviceLocation": "150995751", "arriveTime": 1769914066}, {"isHalf": 0, "startDeviceLocation": "150995733", "destDeviceLocation": "150995751", "arriveTime": 1769914366}, {"isHalf": 0, "startDeviceLocation": "150995733", "destDeviceLocation": "150995751", "arriveTime": 1769914666}, {"isHalf": 0, "startDeviceLocation": "150995733", "destDeviceLocation": "150995751", "arriveTime": 1769914966}, {"isHalf": 0, "startDeviceLocation": "150995733", "destDeviceLocation": "150995751", "arriveTime": 1769915266}, {"isHalf": 0, "startDeviceLocation": "150995733", "destDeviceLocation": "150995751", "arriveTime": 1769915566}, {"isHalf": 0, "startDeviceLocation": "150995733", "destDeviceLocation": "150995751", "arriveTime": 1769915866}, {"isHalf": 0, "startDeviceLocation": "150995733", "destDeviceLocation": "150995751", "arriveTime": 1769916196}, {"isHalf": 0, "startDeviceLocation": "150995733", "destDeviceLocation": "150995751", "arriveTime": 1769916551}, {"isHalf": 0, "startDeviceLocation": "150995733", "destDeviceLocation": "150995751", "arriveTime": 1769916886}, {"isHalf": 0, "startDeviceLocation": "150995733", "destDeviceLocation": "150995751", "arriveTime": 1769917246}, {"isHalf": 0, "startDeviceLocation": "150995733", "destDeviceLocation": "150995751", "arriveTime": 1769917606}, {"isHalf": 0, "startDeviceLocation": "150995733", "destDeviceLocation": "150995751", "arriveTime": 1769917966}, {"isHalf": 0, "startDeviceLocation": "150995733", "destDeviceLocation": "150995751", "arriveTime": 1769918386}, {"isHalf": 0, "startDeviceLocation": "150995733", "destDeviceLocation": "150995751", "arriveTime": 1769918806}, {"isHalf": 0, "startDeviceLocation": "150995733", "destDeviceLocation": "150995751", "arriveTime": 1769919226}, {"isHalf": 0, "startDeviceLocation": "150995733", "destDeviceLocation": "150995751", "arriveTime": 1769919646}, {"isHalf": 0, "startDeviceLocation": "150995733", "destDeviceLocation": "150995751", "arriveTime": 1769920066}, {"isHalf": 0, "startDeviceLocation": "150995733", "destDeviceLocation": "150995751", "arriveTime": 1769920511}, {"isHalf": 0, "startDeviceLocation": "150995733", "destDeviceLocation": "150995751", "arriveTime": 1769920906}, {"isHalf": 0, "startDeviceLocation": "150995733", "destDeviceLocation": "150995751", "arriveTime": 1769921326}, {"isHalf": 0, "startDeviceLocation": "150995733", "destDeviceLocation": "150995751", "arriveTime": 1769921746}, {"isHalf": 0, "startDeviceLocation": "150995733", "destDeviceLocation": "150995751", "arriveTime": 1769922166}, {"isHalf": 0, "startDeviceLocation": "150995733", "destDeviceLocation": "150995751", "arriveTime": 1769922586}, {"isHalf": 0, "startDeviceLocation": "150995733", "destDeviceLocation": "150995751", "arriveTime": 1769923006}, {"isHalf": 0, "startDeviceLocation": "150995733", "destDeviceLocation": "150995751", "arriveTime": 1769923426}, {"isHalf": 0, "startDeviceLocation": "150995733", "destDeviceLocation": "150995751", "arriveTime": 1769923846}, {"isHalf": 0, "startDeviceLocation": "150995733", "destDeviceLocation": "150995751", "arriveTime": 1769924291}, {"isHalf": 0, "startDeviceLocation": "150995733", "destDeviceLocation": "150995751", "arriveTime": 1769924686}, {"isHalf": 0, "startDeviceLocation": "150995733", "destDeviceLocation": "150995751", "arriveTime": 1769925106}, {"isHalf": 0, "startDeviceLocation": "150995733", "destDeviceLocation": "150995751", "arriveTime": 1769925526}, {"isHalf": 0, "startDeviceLocation": "150995733", "destDeviceLocation": "150995751", "arriveTime": 1769925946}, {"isHalf": 0, "startDeviceLocation": "150995733", "destDeviceLocation": "150995751", "arriveTime": 1769926366}, {"isHalf": 0, "startDeviceLocation": "150995733", "destDeviceLocation": "150995751", "arriveTime": 1769926786}, {"isHalf": 0, "startDeviceLocation": "150995733", "destDeviceLocation": "150995751", "arriveTime": 1769927206}, {"isHalf": 0, "startDeviceLocation": "150995733", "destDeviceLocation": "150995751", "arriveTime": 1769927626}, {"isHalf": 0, "startDeviceLocation": "150995733", "destDeviceLocation": "150995751", "arriveTime": 1769928071}, {"isHalf": 0, "startDeviceLocation": "150995733", "destDeviceLocation": "150995751", "arriveTime": 1769928466}, {"isHalf": 0, "startDeviceLocation": "150995733", "destDeviceLocation": "150995751", "arriveTime": 1769928886}, {"isHalf": 0, "startDeviceLocation": "150995733", "destDeviceLocation": "150995751", "arriveTime": 1769929306}, {"isHalf": 0, "startDeviceLocation": "150995733", "destDeviceLocation": "150995751", "arriveTime": 1769929726}, {"isHalf": 0, "startDeviceLocation": "150995733", "destDeviceLocation": "150995751", "arriveTime": 1769930146}, {"isHalf": 0, "startDeviceLocation": "150995733", "destDeviceLocation": "150995751", "arriveTime": 1769930566}, {"isHalf": 0, "startDeviceLocation": "150995733", "destDeviceLocation": "150995751", "arriveTime": 1769930986}, {"isHalf": 0, "startDeviceLocation": "150995733", "destDeviceLocation": "150995751", "arriveTime": 1769931406}, {"isHalf": 0, "startDeviceLocation": "150995733", "destDeviceLocation": "150995751", "arriveTime": 1769931851}, {"isHalf": 0, "startDeviceLocation": "150995733", "destDeviceLocation": "150995751", "arriveTime": 1769932246}, {"isHalf": 0, "startDeviceLocation": "150995733", "destDeviceLocation": "150995751", "arriveTime": 1769932666}, {"isHalf": 0, "startDeviceLocation": "150995733", "destDeviceLocation": "150995751", "arriveTime": 1769933086}, {"isHalf": 0, "startDeviceLocation": "150995733", "destDeviceLocation": "150995751", "arriveTime": 1769933506}, {"isHalf": 0, "startDeviceLocation": "150995733", "destDeviceLocation": "150995751", "arriveTime": 1769933926}, {"isHalf": 0, "startDeviceLocation": "150995733", "destDeviceLocation": "150995751", "arriveTime": 1769934346}, {"isHalf": 0, "startDeviceLocation": "150995733", "destDeviceLocation": "150995751", "arriveTime": 1769934766}, {"isHalf": 0, "startDeviceLocation": "150995733", "destDeviceLocation": "150995751", "arriveTime": 1769935186}, {"isHalf": 0, "startDeviceLocation": "150995733", "destDeviceLocation": "150995751", "arriveTime": 1769935631}, {"isHalf": 0, "startDeviceLocation": "150995733", "destDeviceLocation": "150995751", "arriveTime": 1769936026}, {"isHalf": 0, "startDeviceLocation": "150995733", "destDeviceLocation": "150995751", "arriveTime": 1769936446}, {"isHalf": 0, "startDeviceLocation": "150995733", "destDeviceLocation": "150995751", "arriveTime": 1769936806}, {"isHalf": 0, "startDeviceLocation": "150995733", "destDeviceLocation": "150995751", "arriveTime": 1769937230}, {"isHalf": 0, "startDeviceLocation": "150995733", "destDeviceLocation": "150995751", "arriveTime": 1769937590}, {"isHalf": 0, "startDeviceLocation": "150995733", "destDeviceLocation": "150995751", "arriveTime": 1769937890}, {"isHalf": 0, "startDeviceLocation": "150995733", "destDeviceLocation": "150995751", "arriveTime": 1769938190}, {"isHalf": 0, "startDeviceLocation": "150995733", "destDeviceLocation": "150995751", "arriveTime": 1769938490}, {"isHalf": 0, "startDeviceLocation": "150995733", "destDeviceLocation": "150995751", "arriveTime": 1769938790}, {"isHalf": 0, "startDeviceLocation": "150995733", "destDeviceLocation": "150995751", "arriveTime": 1769939090}, {"isHalf": 0, "startDeviceLocation": "150995733", "destDeviceLocation": "150995751", "arriveTime": 1769939415}, {"isHalf": 0, "startDeviceLocation": "150995733", "destDeviceLocation": "150995751", "arriveTime": 1769939690}, {"isHalf": 0, "startDeviceLocation": "150995733", "destDeviceLocation": "150995751", "arriveTime": 1769939990}, {"isHalf": 0, "startDeviceLocation": "150995733", "destDeviceLocation": "150995751", "arriveTime": 1769940290}, {"isHalf": 0, "startDeviceLocation": "150995733", "destDeviceLocation": "150995751", "arriveTime": 1769940590}, {"isHalf": 0, "startDeviceLocation": "150995733", "destDeviceLocation": "150995751", "arriveTime": 1769940890}, {"isHalf": 0, "startDeviceLocation": "150995733", "destDeviceLocation": "150995751", "arriveTime": 1769941190}, {"isHalf": 0, "startDeviceLocation": "150995733", "destDeviceLocation": "150995751", "arriveTime": 1769941490}, {"isHalf": 0, "startDeviceLocation": "150995733", "destDeviceLocation": "150995751", "arriveTime": 1769941790}, {"isHalf": 0, "startDeviceLocation": "150995733", "destDeviceLocation": "150995751", "arriveTime": 1769942090}, {"isHalf": 0, "startDeviceLocation": "150995733", "destDeviceLocation": "150995751", "arriveTime": 1769942390}, {"isHalf": 0, "startDeviceLocation": "150995733", "destDeviceLocation": "150995751", "arriveTime": 1769942690}, {"isHalf": 0, "startDeviceLocation": "150995733", "destDeviceLocation": "150995751", "arriveTime": 1769942990}, {"isHalf": 0, "startDeviceLocation": "150995733", "destDeviceLocation": "150995751", "arriveTime": 1769943315}, {"isHalf": 0, "startDeviceLocation": "150995733", "destDeviceLocation": "150995751", "arriveTime": 1769943590}, {"isHalf": 0, "startDeviceLocation": "150995733", "destDeviceLocation": "150995751", "arriveTime": 1769943890}, {"isHalf": 0, "startDeviceLocation": "150995733", "destDeviceLocation": "150995751", "arriveTime": 1769944190}, {"isHalf": 0, "startDeviceLocation": "150995733", "destDeviceLocation": "150995751", "arriveTime": 1769944490}, {"isHalf": 0, "startDeviceLocation": "150995733", "destDeviceLocation": "150995751", "arriveTime": 1769944790}, {"isHalf": 0, "startDeviceLocation": "150995733", "destDeviceLocation": "150995751", "arriveTime": 1769945090}, {"isHalf": 0, "startDeviceLocation": "150995733", "destDeviceLocation": "150995751", "arriveTime": 1769945390}, {"isHalf": 0, "startDeviceLocation": "150995733", "destDeviceLocation": "150995751", "arriveTime": 1769945690}, {"isHalf": 0, "startDeviceLocation": "150995733", "destDeviceLocation": "150995751", "arriveTime": 1769945990}, {"isHalf": 0, "startDeviceLocation": "150995733", "destDeviceLocation": "150995751", "arriveTime": 1769946290}, {"isHalf": 0, "startDeviceLocation": "150995733", "destDeviceLocation": "150995751", "arriveTime": 1769946590}, {"isHalf": 0, "startDeviceLocation": "150995733", "destDeviceLocation": "150995751", "arriveTime": 1769946890}, {"isHalf": 0, "startDeviceLocation": "150995733", "destDeviceLocation": "150995751", "arriveTime": 1769947215}, {"isHalf": 0, "startDeviceLocation": "150995733", "destDeviceLocation": "150995751", "arriveTime": 1769947490}, {"isHalf": 0, "startDeviceLocation": "150995733", "destDeviceLocation": "150995751", "arriveTime": 1769947790}, {"isHalf": 0, "startDeviceLocation": "150995733", "destDeviceLocation": "150995751", "arriveTime": 1769948090}, {"isHalf": 0, "startDeviceLocation": "150995733", "destDeviceLocation": "150995751", "arriveTime": 1769948450}, {"isHalf": 0, "startDeviceLocation": "150995733", "destDeviceLocation": "150995751", "arriveTime": 1769948810}, {"isHalf": 0, "startDeviceLocation": "150995733", "destDeviceLocation": "150995751", "arriveTime": 1769949230}, {"isHalf": 0, "startDeviceLocation": "150995733", "destDeviceLocation": "150995751", "arriveTime": 1769949650}, {"isHalf": 0, "startDeviceLocation": "150995733", "destDeviceLocation": "150995751", "arriveTime": 1769950070}, {"isHalf": 0, "startDeviceLocation": "150995733", "destDeviceLocation": "150995751", "arriveTime": 1769950490}, {"isHalf": 0, "startDeviceLocation": "150995733", "destDeviceLocation": "150995751", "arriveTime": 1769950935}, {"isHalf": 0, "startDeviceLocation": "150995733", "destDeviceLocation": "150995751", "arriveTime": 1769951330}, {"isHalf": 0, "startDeviceLocation": "150995733", "destDeviceLocation": "150995751", "arriveTime": 1769951750}, {"isHalf": 0, "startDeviceLocation": "150995733", "destDeviceLocation": "150995751", "arriveTime": 1769952170}, {"isHalf": 0, "startDeviceLocation": "150995733", "destDeviceLocation": "150995751", "arriveTime": 1769952590}, {"isHalf": 0, "startDeviceLocation": "150995733", "destDeviceLocation": "150995751", "arriveTime": 1769953010}, {"isHalf": 0, "startDeviceLocation": "150995733", "destDeviceLocation": "150995751", "arriveTime": 1769953430}, {"isHalf": 0, "startDeviceLocation": "150995733", "destDeviceLocation": "150995751", "arriveTime": 1769953850}, {"isHalf": 0, "startDeviceLocation": "150995733", "destDeviceLocation": "150995751", "arriveTime": 1769954270}, {"isHalf": 0, "startDeviceLocation": "150995733", "destDeviceLocation": "150995751", "arriveTime": 1769954715}, {"isHalf": 0, "startDeviceLocation": "150995733", "destDeviceLocation": "150995751", "arriveTime": 1769955110}, {"isHalf": 0, "startDeviceLocation": "150995733", "destDeviceLocation": "150995751", "arriveTime": 1769955530}, {"isHalf": 0, "startDeviceLocation": "150995733", "destDeviceLocation": "150995751", "arriveTime": 1769955950}, {"isHalf": 0, "startDeviceLocation": "150995733", "destDeviceLocation": "150995751", "arriveTime": 1769956370}, {"isHalf": 0, "startDeviceLocation": "150995733", "destDeviceLocation": "150995751", "arriveTime": 1769956790}, {"isHalf": 0, "startDeviceLocation": "150995733", "destDeviceLocation": "150995751", "arriveTime": 1769957210}, {"isHalf": 0, "startDeviceLocation": "150995733", "destDeviceLocation": "150995751", "arriveTime": 1769957630}, {"isHalf": 0, "startDeviceLocation": "150995733", "destDeviceLocation": "150995751", "arriveTime": 1769958050}, {"isHalf": 0, "startDeviceLocation": "150995733", "destDeviceLocation": "150995751", "arriveTime": 1769958531}, {"isHalf": 0, "startDeviceLocation": "150995733", "destDeviceLocation": "150995751", "arriveTime": 1769958986}, {"isHalf": 0, "startDeviceLocation": "150995733", "destDeviceLocation": "150995751", "arriveTime": 1769959466}, {"isHalf": 0, "startDeviceLocation": "150995733", "destDeviceLocation": "150995751", "arriveTime": 1769959946}, {"isHalf": 0, "startDeviceLocation": "150995733", "destDeviceLocation": "150995751", "arriveTime": 1769960491}]}, {"isWeekDay": 1, "timetables": [{"isHalf": 0, "startDeviceLocation": "150995733", "destDeviceLocation": "150995751", "arriveTime": 1770241891}, {"isHalf": 0, "startDeviceLocation": "150995733", "destDeviceLocation": "150995751", "arriveTime": 1770242436}, {"isHalf": 0, "startDeviceLocation": "150995733", "destDeviceLocation": "150995751", "arriveTime": 1770242921}, {"isHalf": 0, "startDeviceLocation": "150995733", "destDeviceLocation": "150995751", "arriveTime": 1770243396}, {"isHalf": 0, "startDeviceLocation": "150995733", "destDeviceLocation": "150995751", "arriveTime": 1770243876}, {"isHalf": 0, "startDeviceLocation": "150995733", "destDeviceLocation": "150995751", "arriveTime": 1770244356}, {"isHalf": 0, "startDeviceLocation": "150995733", "destDeviceLocation": "150995751", "arriveTime": 1770244836}, {"isHalf": 0, "startDeviceLocation": "150995733", "destDeviceLocation": "150995751", "arriveTime": 1770245316}, {"isHalf": 0, "startDeviceLocation": "150995733", "destDeviceLocation": "150995751", "arriveTime": 1770245796}, {"isHalf": 0, "startDeviceLocation": "150995733", "destDeviceLocation": "150995751", "arriveTime": 1770246276}, {"isHalf": 0, "startDeviceLocation": "150995733", "destDeviceLocation": "150995751", "arriveTime": 1770246582}, {"isHalf": 0, "startDeviceLocation": "150995733", "destDeviceLocation": "150995751", "arriveTime": 1770246822}, {"isHalf": 0, "startDeviceLocation": "150995733", "destDeviceLocation": "150995751", "arriveTime": 1770247062}, {"isHalf": 0, "startDeviceLocation": "150995733", "destDeviceLocation": "150995751", "arriveTime": 1770247302}, {"isHalf": 0, "startDeviceLocation": "150995733", "destDeviceLocation": "150995751", "arriveTime": 1770247542}, {"isHalf": 0, "startDeviceLocation": "150995733", "destDeviceLocation": "150995751", "arriveTime": 1770247782}, {"isHalf": 0, "startDeviceLocation": "150995733", "destDeviceLocation": "150995751", "arriveTime": 1770248022}, {"isHalf": 0, "startDeviceLocation": "150995733", "destDeviceLocation": "150995751", "arriveTime": 1770248262}, {"isHalf": 0, "startDeviceLocation": "150995733", "destDeviceLocation": "150995751", "arriveTime": 1770248502}, {"isHalf": 0, "startDeviceLocation": "150995733", "destDeviceLocation": "150995751", "arriveTime": 1770248742}, {"isHalf": 0, "startDeviceLocation": "150995733", "destDeviceLocation": "150995751", "arriveTime": 1770248982}, {"isHalf": 0, "startDeviceLocation": "150995733", "destDeviceLocation": "150995751", "arriveTime": 1770249222}, {"isHalf": 0, "startDeviceLocation": "150995733", "destDeviceLocation": "150995751", "arriveTime": 1770249462}, {"isHalf": 0, "startDeviceLocation": "150995733", "destDeviceLocation": "150995751", "arriveTime": 1770249702}, {"isHalf": 0, "startDeviceLocation": "150995733", "destDeviceLocation": "150995751", "arriveTime": 1770249942}, {"isHalf": 0, "startDeviceLocation": "150995733", "destDeviceLocation": "150995751", "arriveTime": 1770250182}, {"isHalf": 0, "startDeviceLocation": "150995733", "destDeviceLocation": "150995751", "arriveTime": 1770250422}, {"isHalf": 0, "startDeviceLocation": "150995733", "destDeviceLocation": "150995751", "arriveTime": 1770250662}, {"isHalf": 0, "startDeviceLocation": "150995733", "destDeviceLocation": "150995751", "arriveTime": 1770250902}, {"isHalf": 0, "startDeviceLocation": "150995733", "destDeviceLocation": "150995751", "arriveTime": 1770251142}, {"isHalf": 0, "startDeviceLocation": "150995733", "destDeviceLocation": "150995751", "arriveTime": 1770251382}, {"isHalf": 0, "startDeviceLocation": "150995733", "destDeviceLocation": "150995751", "arriveTime": 1770251622}, {"isHalf": 0, "startDeviceLocation": "150995733", "destDeviceLocation": "150995751", "arriveTime": 1770251862}, {"isHalf": 0, "startDeviceLocation": "150995733", "destDeviceLocation": "150995751", "arriveTime": 1770252102}, {"isHalf": 0, "startDeviceLocation": "150995733", "destDeviceLocation": "150995751", "arriveTime": 1770252342}, {"isHalf": 0, "startDeviceLocation": "150995733", "destDeviceLocation": "150995751", "arriveTime": 1770252582}, {"isHalf": 0, "startDeviceLocation": "150995733", "destDeviceLocation": "150995751", "arriveTime": 1770252822}, {"isHalf": 0, "startDeviceLocation": "150995733", "destDeviceLocation": "150995751", "arriveTime": 1770253062}, {"isHalf": 0, "startDeviceLocation": "150995733", "destDeviceLocation": "150995751", "arriveTime": 1770253302}, {"isHalf": 0, "startDeviceLocation": "150995733", "destDeviceLocation": "150995751", "arriveTime": 1770253542}, {"isHalf": 0, "startDeviceLocation": "150995733", "destDeviceLocation": "150995751", "arriveTime": 1770253782}, {"isHalf": 0, "startDeviceLocation": "150995733", "destDeviceLocation": "150995751", "arriveTime": 1770254022}, {"isHalf": 0, "startDeviceLocation": "150995733", "destDeviceLocation": "150995751", "arriveTime": 1770254262}, {"isHalf": 0, "startDeviceLocation": "150995733", "destDeviceLocation": "150995751", "arriveTime": 1770254562}, {"isHalf": 0, "startDeviceLocation": "150995733", "destDeviceLocation": "150995751", "arriveTime": 1770254862}, {"isHalf": 0, "startDeviceLocation": "150995733", "destDeviceLocation": "150995751", "arriveTime": 1770255162}, {"isHalf": 0, "startDeviceLocation": "150995733", "destDeviceLocation": "150995751", "arriveTime": 1770255462}, {"isHalf": 0, "startDeviceLocation": "150995733", "destDeviceLocation": "150995751", "arriveTime": 1770255762}, {"isHalf": 0, "startDeviceLocation": "150995733", "destDeviceLocation": "150995751", "arriveTime": 1770256122}, {"isHalf": 0, "startDeviceLocation": "150995733", "destDeviceLocation": "150995751", "arriveTime": 1770256542}, {"isHalf": 0, "startDeviceLocation": "150995733", "destDeviceLocation": "150995751", "arriveTime": 1770256962}, {"isHalf": 0, "startDeviceLocation": "150995733", "destDeviceLocation": "150995751", "arriveTime": 1770257382}, {"isHalf": 0, "startDeviceLocation": "150995733", "destDeviceLocation": "150995751", "arriveTime": 1770257802}, {"isHalf": 0, "startDeviceLocation": "150995733", "destDeviceLocation": "150995751", "arriveTime": 1770258222}, {"isHalf": 0, "startDeviceLocation": "150995733", "destDeviceLocation": "150995751", "arriveTime": 1770258642}, {"isHalf": 0, "startDeviceLocation": "150995733", "destDeviceLocation": "150995751", "arriveTime": 1770259062}, {"isHalf": 0, "startDeviceLocation": "150995733", "destDeviceLocation": "150995751", "arriveTime": 1770259482}, {"isHalf": 0, "startDeviceLocation": "150995733", "destDeviceLocation": "150995751", "arriveTime": 1770259902}, {"isHalf": 0, "startDeviceLocation": "150995733", "destDeviceLocation": "150995751", "arriveTime": 1770260322}, {"isHalf": 0, "startDeviceLocation": "150995733", "destDeviceLocation": "150995751", "arriveTime": 1770260742}, {"isHalf": 0, "startDeviceLocation": "150995733", "destDeviceLocation": "150995751", "arriveTime": 1770261162}, {"isHalf": 0, "startDeviceLocation": "150995733", "destDeviceLocation": "150995751", "arriveTime": 1770261582}, {"isHalf": 0, "startDeviceLocation": "150995733", "destDeviceLocation": "150995751", "arriveTime": 1770262002}, {"isHalf": 0, "startDeviceLocation": "150995733", "destDeviceLocation": "150995751", "arriveTime": 1770262422}, {"isHalf": 0, "startDeviceLocation": "150995733", "destDeviceLocation": "150995751", "arriveTime": 1770262842}, {"isHalf": 0, "startDeviceLocation": "150995733", "destDeviceLocation": "150995751", "arriveTime": 1770263262}, {"isHalf": 0, "startDeviceLocation": "150995733", "destDeviceLocation": "150995751", "arriveTime": 1770263682}, {"isHalf": 0, "startDeviceLocation": "150995733", "destDeviceLocation": "150995751", "arriveTime": 1770264102}, {"isHalf": 0, "startDeviceLocation": "150995733", "destDeviceLocation": "150995751", "arriveTime": 1770264522}, {"isHalf": 0, "startDeviceLocation": "150995733", "destDeviceLocation": "150995751", "arriveTime": 1770264942}, {"isHalf": 0, "startDeviceLocation": "150995733", "destDeviceLocation": "150995751", "arriveTime": 1770265362}, {"isHalf": 0, "startDeviceLocation": "150995733", "destDeviceLocation": "150995751", "arriveTime": 1770265782}, {"isHalf": 0, "startDeviceLocation": "150995733", "destDeviceLocation": "150995751", "arriveTime": 1770266202}, {"isHalf": 0, "startDeviceLocation": "150995733", "destDeviceLocation": "150995751", "arriveTime": 1770266622}, {"isHalf": 0, "startDeviceLocation": "150995733", "destDeviceLocation": "150995751", "arriveTime": 1770267042}, {"isHalf": 0, "startDeviceLocation": "150995733", "destDeviceLocation": "150995751", "arriveTime": 1770267462}, {"isHalf": 0, "startDeviceLocation": "150995733", "destDeviceLocation": "150995751", "arriveTime": 1770267882}, {"isHalf": 0, "startDeviceLocation": "150995733", "destDeviceLocation": "150995751", "arriveTime": 1770268302}, {"isHalf": 0, "startDeviceLocation": "150995733", "destDeviceLocation": "150995751", "arriveTime": 1770268722}, {"isHalf": 0, "startDeviceLocation": "150995733", "destDeviceLocation": "150995751", "arriveTime": 1770269142}, {"isHalf": 0, "startDeviceLocation": "150995733", "destDeviceLocation": "150995751", "arriveTime": 1770269562}, {"isHalf": 0, "startDeviceLocation": "150995733", "destDeviceLocation": "150995751", "arriveTime": 1770269982}, {"isHalf": 0, "startDeviceLocation": "150995733", "destDeviceLocation": "150995751", "arriveTime": 1770270402}, {"isHalf": 0, "startDeviceLocation": "150995733", "destDeviceLocation": "150995751", "arriveTime": 1770270822}, {"isHalf": 0, "startDeviceLocation": "150995733", "destDeviceLocation": "150995751", "arriveTime": 1770271242}, {"isHalf": 0, "startDeviceLocation": "150995733", "destDeviceLocation": "150995751", "arriveTime": 1770271662}, {"isHalf": 0, "startDeviceLocation": "150995733", "destDeviceLocation": "150995751", "arriveTime": 1770272082}, {"isHalf": 0, "startDeviceLocation": "150995733", "destDeviceLocation": "150995751", "arriveTime": 1770272502}, {"isHalf": 0, "startDeviceLocation": "150995733", "destDeviceLocation": "150995751", "arriveTime": 1770272922}, {"isHalf": 0, "startDeviceLocation": "150995733", "destDeviceLocation": "150995751", "arriveTime": 1770273342}, {"isHalf": 0, "startDeviceLocation": "150995733", "destDeviceLocation": "150995751", "arriveTime": 1770273762}, {"isHalf": 0, "startDeviceLocation": "150995733", "destDeviceLocation": "150995751", "arriveTime": 1770274182}, {"isHalf": 0, "startDeviceLocation": "150995733", "destDeviceLocation": "150995751", "arriveTime": 1770274602}, {"isHalf": 0, "startDeviceLocation": "150995733", "destDeviceLocation": "150995751", "arriveTime": 1770275022}, {"isHalf": 0, "startDeviceLocation": "150995733", "destDeviceLocation": "150995751", "arriveTime": 1770275442}, {"isHalf": 0, "startDeviceLocation": "150995733", "destDeviceLocation": "150995751", "arriveTime": 1770275862}, {"isHalf": 0, "startDeviceLocation": "150995733", "destDeviceLocation": "150995751", "arriveTime": 1770276282}, {"isHalf": 0, "startDeviceLocation": "150995733", "destDeviceLocation": "150995751", "arriveTime": 1770276702}, {"isHalf": 0, "startDeviceLocation": "150995733", "destDeviceLocation": "150995751", "arriveTime": 1770277122}, {"isHalf": 0, "startDeviceLocation": "150995733", "destDeviceLocation": "150995751", "arriveTime": 1770277542}, {"isHalf": 0, "startDeviceLocation": "150995733", "destDeviceLocation": "150995751", "arriveTime": 1770277962}, {"isHalf": 0, "startDeviceLocation": "150995733", "destDeviceLocation": "150995751", "arriveTime": 1770278382}, {"isHalf": 0, "startDeviceLocation": "150995733", "destDeviceLocation": "150995751", "arriveTime": 1770278802}, {"isHalf": 0, "startDeviceLocation": "150995733", "destDeviceLocation": "150995751", "arriveTime": 1770279222}, {"isHalf": 0, "startDeviceLocation": "150995733", "destDeviceLocation": "150995751", "arriveTime": 1770279642}, {"isHalf": 0, "startDeviceLocation": "150995733", "destDeviceLocation": "150995751", "arriveTime": 1770280062}, {"isHalf": 0, "startDeviceLocation": "150995733", "destDeviceLocation": "150995751", "arriveTime": 1770280482}, {"isHalf": 0, "startDeviceLocation": "150995733", "destDeviceLocation": "150995751", "arriveTime": 1770280902}, {"isHalf": 0, "startDeviceLocation": "150995733", "destDeviceLocation": "150995751", "arriveTime": 1770281266}, {"isHalf": 0, "startDeviceLocation": "150995733", "destDeviceLocation": "150995751", "arriveTime": 1770281712}, {"isHalf": 0, "startDeviceLocation": "150995733", "destDeviceLocation": "150995751", "arriveTime": 1770282162}, {"isHalf": 0, "startDeviceLocation": "150995733", "destDeviceLocation": "150995751", "arriveTime": 1770282582}, {"isHalf": 0, "startDeviceLocation": "150995733", "destDeviceLocation": "150995751", "arriveTime": 1770282942}, {"isHalf": 0, "startDeviceLocation": "150995733", "destDeviceLocation": "150995751", "arriveTime": 1770283182}, {"isHalf": 0, "startDeviceLocation": "150995733", "destDeviceLocation": "150995751", "arriveTime": 1770283422}, {"isHalf": 0, "startDeviceLocation": "150995733", "destDeviceLocation": "150995751", "arriveTime": 1770283662}, {"isHalf": 0, "startDeviceLocation": "150995733", "destDeviceLocation": "150995751", "arriveTime": 1770283902}, {"isHalf": 0, "startDeviceLocation": "150995733", "destDeviceLocation": "150995751", "arriveTime": 1770284142}, {"isHalf": 0, "startDeviceLocation": "150995733", "destDeviceLocation": "150995751", "arriveTime": 1770284382}, {"isHalf": 0, "startDeviceLocation": "150995733", "destDeviceLocation": "150995751", "arriveTime": 1770284622}, {"isHalf": 0, "startDeviceLocation": "150995733", "destDeviceLocation": "150995751", "arriveTime": 1770284862}, {"isHalf": 0, "startDeviceLocation": "150995733", "destDeviceLocation": "150995751", "arriveTime": 1770285102}, {"isHalf": 0, "startDeviceLocation": "150995733", "destDeviceLocation": "150995751", "arriveTime": 1770285342}, {"isHalf": 0, "startDeviceLocation": "150995733", "destDeviceLocation": "150995751", "arriveTime": 1770285582}, {"isHalf": 0, "startDeviceLocation": "150995733", "destDeviceLocation": "150995751", "arriveTime": 1770285822}, {"isHalf": 0, "startDeviceLocation": "150995733", "destDeviceLocation": "150995751", "arriveTime": 1770286062}, {"isHalf": 0, "startDeviceLocation": "150995733", "destDeviceLocation": "150995751", "arriveTime": 1770286302}, {"isHalf": 0, "startDeviceLocation": "150995733", "destDeviceLocation": "150995751", "arriveTime": 1770286542}, {"isHalf": 0, "startDeviceLocation": "150995733", "destDeviceLocation": "150995751", "arriveTime": 1770286782}, {"isHalf": 0, "startDeviceLocation": "150995733", "destDeviceLocation": "150995751", "arriveTime": 1770287022}, {"isHalf": 0, "startDeviceLocation": "150995733", "destDeviceLocation": "150995751", "arriveTime": 1770287262}, {"isHalf": 0, "startDeviceLocation": "150995733", "destDeviceLocation": "150995751", "arriveTime": 1770287502}, {"isHalf": 0, "startDeviceLocation": "150995733", "destDeviceLocation": "150995751", "arriveTime": 1770287742}, {"isHalf": 0, "startDeviceLocation": "150995733", "destDeviceLocation": "150995751", "arriveTime": 1770287982}, {"isHalf": 0, "startDeviceLocation": "150995733", "destDeviceLocation": "150995751", "arriveTime": 1770288222}, {"isHalf": 0, "startDeviceLocation": "150995733", "destDeviceLocation": "150995751", "arriveTime": 1770288462}, {"isHalf": 0, "startDeviceLocation": "150995733", "destDeviceLocation": "150995751", "arriveTime": 1770288702}, {"isHalf": 0, "startDeviceLocation": "150995733", "destDeviceLocation": "150995751", "arriveTime": 1770288942}, {"isHalf": 0, "startDeviceLocation": "150995733", "destDeviceLocation": "150995751", "arriveTime": 1770289182}, {"isHalf": 0, "startDeviceLocation": "150995733", "destDeviceLocation": "150995751", "arriveTime": 1770289422}, {"isHalf": 0, "startDeviceLocation": "150995733", "destDeviceLocation": "150995751", "arriveTime": 1770289662}, {"isHalf": 0, "startDeviceLocation": "150995733", "destDeviceLocation": "150995751", "arriveTime": 1770289902}, {"isHalf": 0, "startDeviceLocation": "150995733", "destDeviceLocation": "150995751", "arriveTime": 1770290142}, {"isHalf": 0, "startDeviceLocation": "150995733", "destDeviceLocation": "150995751", "arriveTime": 1770290382}, {"isHalf": 0, "startDeviceLocation": "150995733", "destDeviceLocation": "150995751", "arriveTime": 1770290622}, {"isHalf": 0, "startDeviceLocation": "150995733", "destDeviceLocation": "150995751", "arriveTime": 1770290862}, {"isHalf": 0, "startDeviceLocation": "150995733", "destDeviceLocation": "150995751", "arriveTime": 1770291102}, {"isHalf": 0, "startDeviceLocation": "150995733", "destDeviceLocation": "150995751", "arriveTime": 1770291342}, {"isHalf": 0, "startDeviceLocation": "150995733", "destDeviceLocation": "150995751", "arriveTime": 1770291582}, {"isHalf": 0, "startDeviceLocation": "150995733", "destDeviceLocation": "150995751", "arriveTime": 1770291822}, {"isHalf": 0, "startDeviceLocation": "150995733", "destDeviceLocation": "150995751", "arriveTime": 1770292062}, {"isHalf": 0, "startDeviceLocation": "150995733", "destDeviceLocation": "150995751", "arriveTime": 1770292302}, {"isHalf": 0, "startDeviceLocation": "150995733", "destDeviceLocation": "150995751", "arriveTime": 1770292602}, {"isHalf": 0, "startDeviceLocation": "150995733", "destDeviceLocation": "150995751", "arriveTime": 1770292902}, {"isHalf": 0, "startDeviceLocation": "150995733", "destDeviceLocation": "150995751", "arriveTime": 1770293202}, {"isHalf": 0, "startDeviceLocation": "150995733", "destDeviceLocation": "150995751", "arriveTime": 1770293562}, {"isHalf": 0, "startDeviceLocation": "150995733", "destDeviceLocation": "150995751", "arriveTime": 1770293892}, {"isHalf": 0, "startDeviceLocation": "150995733", "destDeviceLocation": "150995751", "arriveTime": 1770294222}, {"isHalf": 0, "startDeviceLocation": "150995733", "destDeviceLocation": "150995751", "arriveTime": 1770294552}, {"isHalf": 0, "startDeviceLocation": "150995733", "destDeviceLocation": "150995751", "arriveTime": 1770294882}, {"isHalf": 0, "startDeviceLocation": "150995733", "destDeviceLocation": "150995751", "arriveTime": 1770295212}, {"isHalf": 0, "startDeviceLocation": "150995733", "destDeviceLocation": "150995751", "arriveTime": 1770295602}, {"isHalf": 0, "startDeviceLocation": "150995733", "destDeviceLocation": "150995751", "arriveTime": 1770296022}, {"isHalf": 0, "startDeviceLocation": "150995733", "destDeviceLocation": "150995751", "arriveTime": 1770296442}, {"isHalf": 0, "startDeviceLocation": "150995733", "destDeviceLocation": "150995751", "arriveTime": 1770296862}, {"isHalf": 0, "startDeviceLocation": "150995733", "destDeviceLocation": "150995751", "arriveTime": 1770297282}, {"isHalf": 0, "startDeviceLocation": "150995733", "destDeviceLocation": "150995751", "arriveTime": 1770297702}, {"isHalf": 0, "startDeviceLocation": "150995733", "destDeviceLocation": "150995751", "arriveTime": 1770298122}, {"isHalf": 0, "startDeviceLocation": "150995733", "destDeviceLocation": "150995751", "arriveTime": 1770298542}, {"isHalf": 0, "startDeviceLocation": "150995733", "destDeviceLocation": "150995751", "arriveTime": 1770298962}, {"isHalf": 0, "startDeviceLocation": "150995733", "destDeviceLocation": "150995751", "arriveTime": 1770299382}, {"isHalf": 0, "startDeviceLocation": "150995733", "destDeviceLocation": "150995751", "arriveTime": 1770299802}, {"isHalf": 0, "startDeviceLocation": "150995733", "destDeviceLocation": "150995751", "arriveTime": 1770300222}, {"isHalf": 0, "startDeviceLocation": "150995733", "destDeviceLocation": "150995751", "arriveTime": 1770300642}, {"isHalf": 0, "startDeviceLocation": "150995733", "destDeviceLocation": "150995751", "arriveTime": 1770301062}, {"isHalf": 0, "startDeviceLocation": "150995733", "destDeviceLocation": "150995751", "arriveTime": 1770301482}, {"isHalf": 0, "startDeviceLocation": "150995733", "destDeviceLocation": "150995751", "arriveTime": 1770301902}, {"isHalf": 0, "startDeviceLocation": "150995733", "destDeviceLocation": "150995751", "arriveTime": 1770302322}, {"isHalf": 0, "startDeviceLocation": "150995733", "destDeviceLocation": "150995751", "arriveTime": 1770302742}, {"isHalf": 0, "startDeviceLocation": "150995733", "destDeviceLocation": "150995751", "arriveTime": 1770303162}, {"isHalf": 0, "startDeviceLocation": "150995733", "destDeviceLocation": "150995751", "arriveTime": 1770303582}, {"isHalf": 0, "startDeviceLocation": "150995733", "destDeviceLocation": "150995751", "arriveTime": 1770304062}, {"isHalf": 0, "startDeviceLocation": "150995733", "destDeviceLocation": "150995751", "arriveTime": 1770304566}, {"isHalf": 0, "startDeviceLocation": "150995733", "destDeviceLocation": "150995751", "arriveTime": 1770305046}, {"isHalf": 0, "startDeviceLocation": "150995733", "destDeviceLocation": "150995751", "arriveTime": 1770305526}, {"isHalf": 0, "startDeviceLocation": "150995733", "destDeviceLocation": "150995751", "arriveTime": 1770306091}]}]}]}]