[{"deviceLocation": "150999079", "locations": [{"directDeviceLocation": "150999119", "direction": [{"isWeekDay": 0, "timetables": [{"isHalf": 0, "startDeviceLocation": "150999061", "destDeviceLocation": "150999119", "arriveTime": 1769895680}, {"isHalf": 0, "startDeviceLocation": "150999061", "destDeviceLocation": "150999119", "arriveTime": 1769896160}, {"isHalf": 0, "startDeviceLocation": "150999061", "destDeviceLocation": "150999119", "arriveTime": 1769896640}, {"isHalf": 0, "startDeviceLocation": "150999061", "destDeviceLocation": "150999119", "arriveTime": 1769897120}, {"isHalf": 0, "startDeviceLocation": "150999061", "destDeviceLocation": "150999119", "arriveTime": 1769897600}, {"isHalf": 0, "startDeviceLocation": "150999061", "destDeviceLocation": "150999119", "arriveTime": 1769898080}, {"isHalf": 0, "startDeviceLocation": "150999061", "destDeviceLocation": "150999119", "arriveTime": 1769898560}, {"isHalf": 0, "startDeviceLocation": "150999061", "destDeviceLocation": "150999119", "arriveTime": 1769899040}, {"isHalf": 0, "startDeviceLocation": "150999061", "destDeviceLocation": "150999119", "arriveTime": 1769899520}, {"isHalf": 0, "startDeviceLocation": "150999061", "destDeviceLocation": "150999119", "arriveTime": 1769900000}, {"isHalf": 0, "startDeviceLocation": "150999061", "destDeviceLocation": "150999119", "arriveTime": 1769900480}, {"isHalf": 0, "startDeviceLocation": "150999061", "destDeviceLocation": "150999119", "arriveTime": 1769900960}, {"isHalf": 0, "startDeviceLocation": "150999061", "destDeviceLocation": "150999119", "arriveTime": 1769901440}, {"isHalf": 0, "startDeviceLocation": "150999061", "destDeviceLocation": "150999119", "arriveTime": 1769901920}, {"isHalf": 0, "startDeviceLocation": "150999061", "destDeviceLocation": "150999119", "arriveTime": 1769902400}, {"isHalf": 0, "startDeviceLocation": "150999061", "destDeviceLocation": "150999119", "arriveTime": 1769902880}, {"isHalf": 0, "startDeviceLocation": "150999061", "destDeviceLocation": "150999119", "arriveTime": 1769903360}, {"isHalf": 0, "startDeviceLocation": "150999061", "destDeviceLocation": "150999119", "arriveTime": 1769903840}, {"isHalf": 0, "startDeviceLocation": "150999061", "destDeviceLocation": "150999119", "arriveTime": 1769904320}, {"isHalf": 0, "startDeviceLocation": "150999061", "destDeviceLocation": "150999119", "arriveTime": 1769904800}, {"isHalf": 0, "startDeviceLocation": "150999061", "destDeviceLocation": "150999119", "arriveTime": 1769905280}, {"isHalf": 0, "startDeviceLocation": "150999061", "destDeviceLocation": "150999119", "arriveTime": 1769905760}, {"isHalf": 0, "startDeviceLocation": "150999061", "destDeviceLocation": "150999119", "arriveTime": 1769906240}, {"isHalf": 0, "startDeviceLocation": "150999061", "destDeviceLocation": "150999119", "arriveTime": 1769906720}, {"isHalf": 0, "startDeviceLocation": "150999061", "destDeviceLocation": "150999119", "arriveTime": 1769907200}, {"isHalf": 0, "startDeviceLocation": "150999061", "destDeviceLocation": "150999119", "arriveTime": 1769907680}, {"isHalf": 0, "startDeviceLocation": "150999061", "destDeviceLocation": "150999119", "arriveTime": 1769908160}, {"isHalf": 0, "startDeviceLocation": "150999061", "destDeviceLocation": "150999119", "arriveTime": 1769908640}, {"isHalf": 0, "startDeviceLocation": "150999061", "destDeviceLocation": "150999119", "arriveTime": 1769909120}, {"isHalf": 0, "startDeviceLocation": "150999061", "destDeviceLocation": "150999119", "arriveTime": 1769909600}, {"isHalf": 0, "startDeviceLocation": "150999061", "destDeviceLocation": "150999119", "arriveTime": 1769910080}, {"isHalf": 0, "startDeviceLocation": "150999061", "destDeviceLocation": "150999119", "arriveTime": 1769910560}, {"isHalf": 0, "startDeviceLocation": "150999061", "destDeviceLocation": "150999119", "arriveTime": 1769911040}, {"isHalf": 0, "startDeviceLocation": "150999061", "destDeviceLocation": "150999119", "arriveTime": 1769911520}, {"isHalf": 0, "startDeviceLocation": "150999061", "destDeviceLocation": "150999119", "arriveTime": 1769912000}, {"isHalf": 0, "startDeviceLocation": "150999061", "destDeviceLocation": "150999119", "arriveTime": 1769912480}, {"isHalf": 0, "startDeviceLocation": "150999061", "destDeviceLocation": "150999119", "arriveTime": 1769912960}, {"isHalf": 0, "startDeviceLocation": "150999061", "destDeviceLocation": "150999119", "arriveTime": 1769913440}, {"isHalf": 0, "startDeviceLocation": "150999061", "destDeviceLocation": "150999119", "arriveTime": 1769913920}, {"isHalf": 0, "startDeviceLocation": "150999061", "destDeviceLocation": "150999119", "arriveTime": 1769914400}, {"isHalf": 0, "startDeviceLocation": "150999061", "destDeviceLocation": "150999119", "arriveTime": 1769914880}, {"isHalf": 0, "startDeviceLocation": "150999061", "destDeviceLocation": "150999119", "arriveTime": 1769915360}, {"isHalf": 0, "startDeviceLocation": "150999061", "destDeviceLocation": "150999119", "arriveTime": 1769915840}, {"isHalf": 0, "startDeviceLocation": "150999061", "destDeviceLocation": "150999119", "arriveTime": 1769916320}, {"isHalf": 0, "startDeviceLocation": "150999061", "destDeviceLocation": "150999119", "arriveTime": 1769916800}, {"isHalf": 0, "startDeviceLocation": "150999061", "destDeviceLocation": "150999119", "arriveTime": 1769917280}, {"isHalf": 0, "startDeviceLocation": "150999061", "destDeviceLocation": "150999119", "arriveTime": 1769917760}, {"isHalf": 0, "startDeviceLocation": "150999061", "destDeviceLocation": "150999119", "arriveTime": 1769918240}, {"isHalf": 0, "startDeviceLocation": "150999061", "destDeviceLocation": "150999119", "arriveTime": 1769918720}, {"isHalf": 0, "startDeviceLocation": "150999061", "destDeviceLocation": "150999119", "arriveTime": 1769919200}, {"isHalf": 0, "startDeviceLocation": "150999061", "destDeviceLocation": "150999119", "arriveTime": 1769919680}, {"isHalf": 0, "startDeviceLocation": "150999061", "destDeviceLocation": "150999119", "arriveTime": 1769920160}, {"isHalf": 0, "startDeviceLocation": "150999061", "destDeviceLocation": "150999119", "arriveTime": 1769920640}, {"isHalf": 0, "startDeviceLocation": "150999061", "destDeviceLocation": "150999119", "arriveTime": 1769921120}, {"isHalf": 0, "startDeviceLocation": "150999061", "destDeviceLocation": "150999119", "arriveTime": 1769921600}, {"isHalf": 0, "startDeviceLocation": "150999061", "destDeviceLocation": "150999119", "arriveTime": 1769922080}, {"isHalf": 0, "startDeviceLocation": "150999061", "destDeviceLocation": "150999119", "arriveTime": 1769922560}, {"isHalf": 0, "startDeviceLocation": "150999061", "destDeviceLocation": "150999119", "arriveTime": 1769923040}, {"isHalf": 0, "startDeviceLocation": "150999061", "destDeviceLocation": "150999119", "arriveTime": 1769923520}, {"isHalf": 0, "startDeviceLocation": "150999061", "destDeviceLocation": "150999119", "arriveTime": 1769924000}, {"isHalf": 0, "startDeviceLocation": "150999061", "destDeviceLocation": "150999119", "arriveTime": 1769924480}, {"isHalf": 0, "startDeviceLocation": "150999061", "destDeviceLocation": "150999119", "arriveTime": 1769924960}, {"isHalf": 0, "startDeviceLocation": "150999061", "destDeviceLocation": "150999119", "arriveTime": 1769925440}, {"isHalf": 0, "startDeviceLocation": "150999061", "destDeviceLocation": "150999119", "arriveTime": 1769925920}, {"isHalf": 0, "startDeviceLocation": "150999061", "destDeviceLocation": "150999119", "arriveTime": 1769926400}, {"isHalf": 0, "startDeviceLocation": "150999061", "destDeviceLocation": "150999119", "arriveTime": 1769926880}, {"isHalf": 0, "startDeviceLocation": "150999061", "destDeviceLocation": "150999119", "arriveTime": 1769927360}, {"isHalf": 0, "startDeviceLocation": "150999061", "destDeviceLocation": "150999119", "arriveTime": 1769927840}, {"isHalf": 0, "startDeviceLocation": "150999061", "destDeviceLocation": "150999119", "arriveTime": 1769928320}, {"isHalf": 0, "startDeviceLocation": "150999061", "destDeviceLocation": "150999119", "arriveTime": 1769928800}, {"isHalf": 0, "startDeviceLocation": "150999061", "destDeviceLocation": "150999119", "arriveTime": 1769929280}, {"isHalf": 0, "startDeviceLocation": "150999061", "destDeviceLocation": "150999119", "arriveTime": 1769929760}, {"isHalf": 0, "startDeviceLocation": "150999061", "destDeviceLocation": "150999119", "arriveTime": 1769930240}, {"isHalf": 0, "startDeviceLocation": "150999061", "destDeviceLocation": "150999119", "arriveTime": 1769930720}, {"isHalf": 0, "startDeviceLocation": "150999061", "destDeviceLocation": "150999119", "arriveTime": 1769931200}, {"isHalf": 0, "startDeviceLocation": "150999061", "destDeviceLocation": "150999119", "arriveTime": 1769931680}, {"isHalf": 0, "startDeviceLocation": "150999061", "destDeviceLocation": "150999119", "arriveTime": 1769932160}, {"isHalf": 0, "startDeviceLocation": "150999061", "destDeviceLocation": "150999119", "arriveTime": 1769932640}, {"isHalf": 0, "startDeviceLocation": "150999061", "destDeviceLocation": "150999119", "arriveTime": 1769933120}, {"isHalf": 0, "startDeviceLocation": "150999061", "destDeviceLocation": "150999119", "arriveTime": 1769933600}, {"isHalf": 0, "startDeviceLocation": "150999061", "destDeviceLocation": "150999119", "arriveTime": 1769934080}, {"isHalf": 0, "startDeviceLocation": "150999061", "destDeviceLocation": "150999119", "arriveTime": 1769934560}, {"isHalf": 0, "startDeviceLocation": "150999061", "destDeviceLocation": "150999119", "arriveTime": 1769935040}, {"isHalf": 0, "startDeviceLocation": "150999061", "destDeviceLocation": "150999119", "arriveTime": 1769935520}, {"isHalf": 0, "startDeviceLocation": "150999061", "destDeviceLocation": "150999119", "arriveTime": 1769936000}, {"isHalf": 0, "startDeviceLocation": "150999061", "destDeviceLocation": "150999119", "arriveTime": 1769936480}, {"isHalf": 0, "startDeviceLocation": "150999061", "destDeviceLocation": "150999119", "arriveTime": 1769936960}, {"isHalf": 0, "startDeviceLocation": "150999061", "destDeviceLocation": "150999119", "arriveTime": 1769937440}, {"isHalf": 0, "startDeviceLocation": "150999061", "destDeviceLocation": "150999119", "arriveTime": 1769937920}, {"isHalf": 0, "startDeviceLocation": "150999061", "destDeviceLocation": "150999119", "arriveTime": 1769938400}, {"isHalf": 0, "startDeviceLocation": "150999061", "destDeviceLocation": "150999119", "arriveTime": 1769938880}, {"isHalf": 0, "startDeviceLocation": "150999061", "destDeviceLocation": "150999119", "arriveTime": 1769939360}, {"isHalf": 0, "startDeviceLocation": "150999061", "destDeviceLocation": "150999119", "arriveTime": 1769939840}, {"isHalf": 0, "startDeviceLocation": "150999061", "destDeviceLocation": "150999119", "arriveTime": 1769940320}, {"isHalf": 0, "startDeviceLocation": "150999061", "destDeviceLocation": "150999119", "arriveTime": 1769940800}, {"isHalf": 0, "startDeviceLocation": "150999061", "destDeviceLocation": "150999119", "arriveTime": 1769941280}, {"isHalf": 0, "startDeviceLocation": "150999061", "destDeviceLocation": "150999119", "arriveTime": 1769941760}, {"isHalf": 0, "startDeviceLocation": "150999061", "destDeviceLocation": "150999119", "arriveTime": 1769942240}, {"isHalf": 0, "startDeviceLocation": "150999061", "destDeviceLocation": "150999119", "arriveTime": 1769942720}, {"isHalf": 0, "startDeviceLocation": "150999061", "destDeviceLocation": "150999119", "arriveTime": 1769943200}, {"isHalf": 0, "startDeviceLocation": "150999061", "destDeviceLocation": "150999119", "arriveTime": 1769943680}, {"isHalf": 0, "startDeviceLocation": "150999061", "destDeviceLocation": "150999119", "arriveTime": 1769944160}, {"isHalf": 0, "startDeviceLocation": "150999061", "destDeviceLocation": "150999119", "arriveTime": 1769944640}, {"isHalf": 0, "startDeviceLocation": "150999061", "destDeviceLocation": "150999119", "arriveTime": 1769945120}, {"isHalf": 0, "startDeviceLocation": "150999061", "destDeviceLocation": "150999119", "arriveTime": 1769945600}, {"isHalf": 0, "startDeviceLocation": "150999061", "destDeviceLocation": "150999119", "arriveTime": 1769946080}, {"isHalf": 0, "startDeviceLocation": "150999061", "destDeviceLocation": "150999119", "arriveTime": 1769946560}, {"isHalf": 0, "startDeviceLocation": "150999061", "destDeviceLocation": "150999119", "arriveTime": 1769947040}, {"isHalf": 0, "startDeviceLocation": "150999061", "destDeviceLocation": "150999119", "arriveTime": 1769947520}, {"isHalf": 0, "startDeviceLocation": "150999061", "destDeviceLocation": "150999119", "arriveTime": 1769948000}, {"isHalf": 0, "startDeviceLocation": "150999061", "destDeviceLocation": "150999119", "arriveTime": 1769948480}, {"isHalf": 0, "startDeviceLocation": "150999061", "destDeviceLocation": "150999119", "arriveTime": 1769948960}, {"isHalf": 0, "startDeviceLocation": "150999061", "destDeviceLocation": "150999119", "arriveTime": 1769949440}, {"isHalf": 0, "startDeviceLocation": "150999061", "destDeviceLocation": "150999119", "arriveTime": 1769949920}, {"isHalf": 0, "startDeviceLocation": "150999061", "destDeviceLocation": "150999119", "arriveTime": 1769950400}, {"isHalf": 0, "startDeviceLocation": "150999061", "destDeviceLocation": "150999119", "arriveTime": 1769950880}, {"isHalf": 0, "startDeviceLocation": "150999061", "destDeviceLocation": "150999119", "arriveTime": 1769951360}, {"isHalf": 0, "startDeviceLocation": "150999061", "destDeviceLocation": "150999119", "arriveTime": 1769951840}, {"isHalf": 0, "startDeviceLocation": "150999061", "destDeviceLocation": "150999119", "arriveTime": 1769952320}, {"isHalf": 0, "startDeviceLocation": "150999061", "destDeviceLocation": "150999119", "arriveTime": 1769952800}, {"isHalf": 0, "startDeviceLocation": "150999061", "destDeviceLocation": "150999119", "arriveTime": 1769953280}, {"isHalf": 0, "startDeviceLocation": "150999061", "destDeviceLocation": "150999119", "arriveTime": 1769953760}, {"isHalf": 0, "startDeviceLocation": "150999061", "destDeviceLocation": "150999119", "arriveTime": 1769954240}, {"isHalf": 0, "startDeviceLocation": "150999061", "destDeviceLocation": "150999119", "arriveTime": 1769954720}, {"isHalf": 0, "startDeviceLocation": "150999061", "destDeviceLocation": "150999119", "arriveTime": 1769955260}, {"isHalf": 0, "startDeviceLocation": "150999061", "destDeviceLocation": "150999119", "arriveTime": 1769955800}, {"isHalf": 0, "startDeviceLocation": "150999061", "destDeviceLocation": "150999119", "arriveTime": 1769956340}, {"isHalf": 0, "startDeviceLocation": "150999061", "destDeviceLocation": "150999119", "arriveTime": 1769956940}, {"isHalf": 0, "startDeviceLocation": "150999061", "destDeviceLocation": "150999119", "arriveTime": 1769957540}, {"isHalf": 0, "startDeviceLocation": "150999061", "destDeviceLocation": "150999119", "arriveTime": 1769958140}]}, {"isWeekDay": 1, "timetables": [{"isHalf": 0, "startDeviceLocation": "150999061", "destDeviceLocation": "150999119", "arriveTime": 1770241280}, {"isHalf": 0, "startDeviceLocation": "150999061", "destDeviceLocation": "150999119", "arriveTime": 1770241760}, {"isHalf": 0, "startDeviceLocation": "150999061", "destDeviceLocation": "150999119", "arriveTime": 1770242240}, {"isHalf": 0, "startDeviceLocation": "150999061", "destDeviceLocation": "150999119", "arriveTime": 1770242660}, {"isHalf": 0, "startDeviceLocation": "150999061", "destDeviceLocation": "150999119", "arriveTime": 1770243080}, {"isHalf": 0, "startDeviceLocation": "150999061", "destDeviceLocation": "150999119", "arriveTime": 1770243500}, {"isHalf": 0, "startDeviceLocation": "150999061", "destDeviceLocation": "150999119", "arriveTime": 1770243920}, {"isHalf": 0, "startDeviceLocation": "150999061", "destDeviceLocation": "150999119", "arriveTime": 1770244340}, {"isHalf": 0, "startDeviceLocation": "150999061", "destDeviceLocation": "150999119", "arriveTime": 1770244760}, {"isHalf": 0, "startDeviceLocation": "150999061", "destDeviceLocation": "150999119", "arriveTime": 1770245180}, {"isHalf": 0, "startDeviceLocation": "150999061", "destDeviceLocation": "150999119", "arriveTime": 1770245600}, {"isHalf": 0, "startDeviceLocation": "150999061", "destDeviceLocation": "150999119", "arriveTime": 1770245960}, {"isHalf": 0, "startDeviceLocation": "150999061", "destDeviceLocation": "150999119", "arriveTime": 1770246320}, {"isHalf": 0, "startDeviceLocation": "150999061", "destDeviceLocation": "150999119", "arriveTime": 1770246680}, {"isHalf": 0, "startDeviceLocation": "150999061", "destDeviceLocation": "150999119", "arriveTime": 1770247040}, {"isHalf": 0, "startDeviceLocation": "150999061", "destDeviceLocation": "150999119", "arriveTime": 1770247400}, {"isHalf": 0, "startDeviceLocation": "150999061", "destDeviceLocation": "150999119", "arriveTime": 1770247760}, {"isHalf": 0, "startDeviceLocation": "150999061", "destDeviceLocation": "150999119", "arriveTime": 1770248120}, {"isHalf": 0, "startDeviceLocation": "150999061", "destDeviceLocation": "150999119", "arriveTime": 1770248480}, {"isHalf": 0, "startDeviceLocation": "150999061", "destDeviceLocation": "150999119", "arriveTime": 1770248840}, {"isHalf": 0, "startDeviceLocation": "150999061", "destDeviceLocation": "150999119", "arriveTime": 1770249200}, {"isHalf": 0, "startDeviceLocation": "150999061", "destDeviceLocation": "150999119", "arriveTime": 1770249560}, {"isHalf": 0, "startDeviceLocation": "150999061", "destDeviceLocation": "150999119", "arriveTime": 1770249920}, {"isHalf": 0, "startDeviceLocation": "150999061", "destDeviceLocation": "150999119", "arriveTime": 1770250280}, {"isHalf": 0, "startDeviceLocation": "150999061", "destDeviceLocation": "150999119", "arriveTime": 1770250640}, {"isHalf": 0, "startDeviceLocation": "150999061", "destDeviceLocation": "150999119", "arriveTime": 1770251000}, {"isHalf": 0, "startDeviceLocation": "150999061", "destDeviceLocation": "150999119", "arriveTime": 1770251360}, {"isHalf": 0, "startDeviceLocation": "150999061", "destDeviceLocation": "150999119", "arriveTime": 1770251720}, {"isHalf": 0, "startDeviceLocation": "150999061", "destDeviceLocation": "150999119", "arriveTime": 1770252080}, {"isHalf": 0, "startDeviceLocation": "150999061", "destDeviceLocation": "150999119", "arriveTime": 1770252440}, {"isHalf": 0, "startDeviceLocation": "150999061", "destDeviceLocation": "150999119", "arriveTime": 1770252800}, {"isHalf": 0, "startDeviceLocation": "150999061", "destDeviceLocation": "150999119", "arriveTime": 1770253160}, {"isHalf": 0, "startDeviceLocation": "150999061", "destDeviceLocation": "150999119", "arriveTime": 1770253580}, {"isHalf": 0, "startDeviceLocation": "150999061", "destDeviceLocation": "150999119", "arriveTime": 1770254000}, {"isHalf": 0, "startDeviceLocation": "150999061", "destDeviceLocation": "150999119", "arriveTime": 1770254420}, {"isHalf": 0, "startDeviceLocation": "150999061", "destDeviceLocation": "150999119", "arriveTime": 1770254900}, {"isHalf": 0, "startDeviceLocation": "150999061", "destDeviceLocation": "150999119", "arriveTime": 1770255380}, {"isHalf": 0, "startDeviceLocation": "150999061", "destDeviceLocation": "150999119", "arriveTime": 1770255860}, {"isHalf": 0, "startDeviceLocation": "150999061", "destDeviceLocation": "150999119", "arriveTime": 1770256340}, {"isHalf": 0, "startDeviceLocation": "150999061", "destDeviceLocation": "150999119", "arriveTime": 1770256820}, {"isHalf": 0, "startDeviceLocation": "150999061", "destDeviceLocation": "150999119", "arriveTime": 1770257300}, {"isHalf": 0, "startDeviceLocation": "150999061", "destDeviceLocation": "150999119", "arriveTime": 1770257780}, {"isHalf": 0, "startDeviceLocation": "150999061", "destDeviceLocation": "150999119", "arriveTime": 1770258260}, {"isHalf": 0, "startDeviceLocation": "150999061", "destDeviceLocation": "150999119", "arriveTime": 1770258740}, {"isHalf": 0, "startDeviceLocation": "150999061", "destDeviceLocation": "150999119", "arriveTime": 1770259220}, {"isHalf": 0, "startDeviceLocation": "150999061", "destDeviceLocation": "150999119", "arriveTime": 1770259700}, {"isHalf": 0, "startDeviceLocation": "150999061", "destDeviceLocation": "150999119", "arriveTime": 1770260180}, {"isHalf": 0, "startDeviceLocation": "150999061", "destDeviceLocation": "150999119", "arriveTime": 1770260660}, {"isHalf": 0, "startDeviceLocation": "150999061", "destDeviceLocation": "150999119", "arriveTime": 1770261140}, {"isHalf": 0, "startDeviceLocation": "150999061", "destDeviceLocation": "150999119", "arriveTime": 1770261620}, {"isHalf": 0, "startDeviceLocation": "150999061", "destDeviceLocation": "150999119", "arriveTime": 1770262100}, {"isHalf": 0, "startDeviceLocation": "150999061", "destDeviceLocation": "150999119", "arriveTime": 1770262580}, {"isHalf": 0, "startDeviceLocation": "150999061", "destDeviceLocation": "150999119", "arriveTime": 1770263060}, {"isHalf": 0, "startDeviceLocation": "150999061", "destDeviceLocation": "150999119", "arriveTime": 1770263540}, {"isHalf": 0, "startDeviceLocation": "150999061", "destDeviceLocation": "150999119", "arriveTime": 1770264020}, {"isHalf": 0, "startDeviceLocation": "150999061", "destDeviceLocation": "150999119", "arriveTime": 1770264500}, {"isHalf": 0, "startDeviceLocation": "150999061", "destDeviceLocation": "150999119", "arriveTime": 1770264980}, {"isHalf": 0, "startDeviceLocation": "150999061", "destDeviceLocation": "150999119", "arriveTime": 1770265460}, {"isHalf": 0, "startDeviceLocation": "150999061", "destDeviceLocation": "150999119", "arriveTime": 1770265940}, {"isHalf": 0, "startDeviceLocation": "150999061", "destDeviceLocation": "150999119", "arriveTime": 1770266420}, {"isHalf": 0, "startDeviceLocation": "150999061", "destDeviceLocation": "150999119", "arriveTime": 1770266900}, {"isHalf": 0, "startDeviceLocation": "150999061", "destDeviceLocation": "150999119", "arriveTime": 1770267380}, {"isHalf": 0, "startDeviceLocation": "150999061", "destDeviceLocation": "150999119", "arriveTime": 1770267860}, {"isHalf": 0, "startDeviceLocation": "150999061", "destDeviceLocation": "150999119", "arriveTime": 1770268340}, {"isHalf": 0, "startDeviceLocation": "150999061", "destDeviceLocation": "150999119", "arriveTime": 1770268820}, {"isHalf": 0, "startDeviceLocation": "150999061", "destDeviceLocation": "150999119", "arriveTime": 1770269300}, {"isHalf": 0, "startDeviceLocation": "150999061", "destDeviceLocation": "150999119", "arriveTime": 1770269780}, {"isHalf": 0, "startDeviceLocation": "150999061", "destDeviceLocation": "150999119", "arriveTime": 1770270260}, {"isHalf": 0, "startDeviceLocation": "150999061", "destDeviceLocation": "150999119", "arriveTime": 1770270740}, {"isHalf": 0, "startDeviceLocation": "150999061", "destDeviceLocation": "150999119", "arriveTime": 1770271220}, {"isHalf": 0, "startDeviceLocation": "150999061", "destDeviceLocation": "150999119", "arriveTime": 1770271700}, {"isHalf": 0, "startDeviceLocation": "150999061", "destDeviceLocation": "150999119", "arriveTime": 1770272180}, {"isHalf": 0, "startDeviceLocation": "150999061", "destDeviceLocation": "150999119", "arriveTime": 1770272660}, {"isHalf": 0, "startDeviceLocation": "150999061", "destDeviceLocation": "150999119", "arriveTime": 1770273140}, {"isHalf": 0, "startDeviceLocation": "150999061", "destDeviceLocation": "150999119", "arriveTime": 1770273620}, {"isHalf": 0, "startDeviceLocation": "150999061", "destDeviceLocation": "150999119", "arriveTime": 1770274100}, {"isHalf": 0, "startDeviceLocation": "150999061", "destDeviceLocation": "150999119", "arriveTime": 1770274580}, {"isHalf": 0, "startDeviceLocation": "150999061", "destDeviceLocation": "150999119", "arriveTime": 1770275060}, {"isHalf": 0, "startDeviceLocation": "150999061", "destDeviceLocation": "150999119", "arriveTime": 1770275540}, {"isHalf": 0, "startDeviceLocation": "150999061", "destDeviceLocation": "150999119", "arriveTime": 1770276020}, {"isHalf": 0, "startDeviceLocation": "150999061", "destDeviceLocation": "150999119", "arriveTime": 1770276500}, {"isHalf": 0, "startDeviceLocation": "150999061", "destDeviceLocation": "150999119", "arriveTime": 1770276980}, {"isHalf": 0, "startDeviceLocation": "150999061", "destDeviceLocation": "150999119", "arriveTime": 1770277460}, {"isHalf": 0, "startDeviceLocation": "150999061", "destDeviceLocation": "150999119", "arriveTime": 1770277940}, {"isHalf": 0, "startDeviceLocation": "150999061", "destDeviceLocation": "150999119", "arriveTime": 1770278420}, {"isHalf": 0, "startDeviceLocation": "150999061", "destDeviceLocation": "150999119", "arriveTime": 1770278900}, {"isHalf": 0, "startDeviceLocation": "150999061", "destDeviceLocation": "150999119", "arriveTime": 1770279380}, {"isHalf": 0, "startDeviceLocation": "150999061", "destDeviceLocation": "150999119", "arriveTime": 1770279860}, {"isHalf": 0, "startDeviceLocation": "150999061", "destDeviceLocation": "150999119", "arriveTime": 1770280340}, {"isHalf": 0, "startDeviceLocation": "150999061", "destDeviceLocation": "150999119", "arriveTime": 1770280820}, {"isHalf": 0, "startDeviceLocation": "150999061", "destDeviceLocation": "150999119", "arriveTime": 1770281300}, {"isHalf": 0, "startDeviceLocation": "150999061", "destDeviceLocation": "150999119", "arriveTime": 1770281780}, {"isHalf": 0, "startDeviceLocation": "150999061", "destDeviceLocation": "150999119", "arriveTime": 1770282200}, {"isHalf": 0, "startDeviceLocation": "150999061", "destDeviceLocation": "150999119", "arriveTime": 1770282620}, {"isHalf": 0, "startDeviceLocation": "150999061", "destDeviceLocation": "150999119", "arriveTime": 1770283040}, {"isHalf": 0, "startDeviceLocation": "150999061", "destDeviceLocation": "150999119", "arriveTime": 1770283460}, {"isHalf": 0, "startDeviceLocation": "150999061", "destDeviceLocation": "150999119", "arriveTime": 1770283880}, {"isHalf": 0, "startDeviceLocation": "150999061", "destDeviceLocation": "150999119", "arriveTime": 1770284240}, {"isHalf": 0, "startDeviceLocation": "150999061", "destDeviceLocation": "150999119", "arriveTime": 1770284600}, {"isHalf": 0, "startDeviceLocation": "150999061", "destDeviceLocation": "150999119", "arriveTime": 1770284960}, {"isHalf": 0, "startDeviceLocation": "150999061", "destDeviceLocation": "150999119", "arriveTime": 1770285320}, {"isHalf": 0, "startDeviceLocation": "150999061", "destDeviceLocation": "150999119", "arriveTime": 1770285680}, {"isHalf": 0, "startDeviceLocation": "150999061", "destDeviceLocation": "150999119", "arriveTime": 1770286040}, {"isHalf": 0, "startDeviceLocation": "150999061", "destDeviceLocation": "150999119", "arriveTime": 1770286400}, {"isHalf": 0, "startDeviceLocation": "150999061", "destDeviceLocation": "150999119", "arriveTime": 1770286760}, {"isHalf": 0, "startDeviceLocation": "150999061", "destDeviceLocation": "150999119", "arriveTime": 1770287120}, {"isHalf": 0, "startDeviceLocation": "150999061", "destDeviceLocation": "150999119", "arriveTime": 1770287480}, {"isHalf": 0, "startDeviceLocation": "150999061", "destDeviceLocation": "150999119", "arriveTime": 1770287840}, {"isHalf": 0, "startDeviceLocation": "150999061", "destDeviceLocation": "150999119", "arriveTime": 1770288200}, {"isHalf": 0, "startDeviceLocation": "150999061", "destDeviceLocation": "150999119", "arriveTime": 1770288560}, {"isHalf": 0, "startDeviceLocation": "150999061", "destDeviceLocation": "150999119", "arriveTime": 1770288920}, {"isHalf": 0, "startDeviceLocation": "150999061", "destDeviceLocation": "150999119", "arriveTime": 1770289280}, {"isHalf": 0, "startDeviceLocation": "150999061", "destDeviceLocation": "150999119", "arriveTime": 1770289640}, {"isHalf": 0, "startDeviceLocation": "150999061", "destDeviceLocation": "150999119", "arriveTime": 1770290000}, {"isHalf": 0, "startDeviceLocation": "150999061", "destDeviceLocation": "150999119", "arriveTime": 1770290360}, {"isHalf": 0, "startDeviceLocation": "150999061", "destDeviceLocation": "150999119", "arriveTime": 1770290720}, {"isHalf": 0, "startDeviceLocation": "150999061", "destDeviceLocation": "150999119", "arriveTime": 1770291080}, {"isHalf": 0, "startDeviceLocation": "150999061", "destDeviceLocation": "150999119", "arriveTime": 1770291440}, {"isHalf": 0, "startDeviceLocation": "150999061", "destDeviceLocation": "150999119", "arriveTime": 1770291860}, {"isHalf": 0, "startDeviceLocation": "150999061", "destDeviceLocation": "150999119", "arriveTime": 1770292280}, {"isHalf": 0, "startDeviceLocation": "150999061", "destDeviceLocation": "150999119", "arriveTime": 1770292700}, {"isHalf": 0, "startDeviceLocation": "150999061", "destDeviceLocation": "150999119", "arriveTime": 1770293120}, {"isHalf": 0, "startDeviceLocation": "150999061", "destDeviceLocation": "150999119", "arriveTime": 1770293600}, {"isHalf": 0, "startDeviceLocation": "150999061", "destDeviceLocation": "150999119", "arriveTime": 1770294080}, {"isHalf": 0, "startDeviceLocation": "150999061", "destDeviceLocation": "150999119", "arriveTime": 1770294560}, {"isHalf": 0, "startDeviceLocation": "150999061", "destDeviceLocation": "150999119", "arriveTime": 1770295040}, {"isHalf": 0, "startDeviceLocation": "150999061", "destDeviceLocation": "150999119", "arriveTime": 1770295520}, {"isHalf": 0, "startDeviceLocation": "150999061", "destDeviceLocation": "150999119", "arriveTime": 1770296000}, {"isHalf": 0, "startDeviceLocation": "150999061", "destDeviceLocation": "150999119", "arriveTime": 1770296480}, {"isHalf": 0, "startDeviceLocation": "150999061", "destDeviceLocation": "150999119", "arriveTime": 1770296960}, {"isHalf": 0, "startDeviceLocation": "150999061", "destDeviceLocation": "150999119", "arriveTime": 1770297440}, {"isHalf": 0, "startDeviceLocation": "150999061", "destDeviceLocation": "150999119", "arriveTime": 1770297920}, {"isHalf": 0, "startDeviceLocation": "150999061", "destDeviceLocation": "150999119", "arriveTime": 1770298400}, {"isHalf": 0, "startDeviceLocation": "150999061", "destDeviceLocation": "150999119", "arriveTime": 1770298880}, {"isHalf": 0, "startDeviceLocation": "150999061", "destDeviceLocation": "150999119", "arriveTime": 1770299360}, {"isHalf": 0, "startDeviceLocation": "150999061", "destDeviceLocation": "150999119", "arriveTime": 1770299840}, {"isHalf": 0, "startDeviceLocation": "150999061", "destDeviceLocation": "150999119", "arriveTime": 1770300320}, {"isHalf": 0, "startDeviceLocation": "150999061", "destDeviceLocation": "150999119", "arriveTime": 1770300860}, {"isHalf": 0, "startDeviceLocation": "150999061", "destDeviceLocation": "150999119", "arriveTime": 1770301400}, {"isHalf": 0, "startDeviceLocation": "150999061", "destDeviceLocation": "150999119", "arriveTime": 1770301940}, {"isHalf": 0, "startDeviceLocation": "150999061", "destDeviceLocation": "150999119", "arriveTime": 1770302540}, {"isHalf": 0, "startDeviceLocation": "150999061", "destDeviceLocation": "150999119", "arriveTime": 1770303140}, {"isHalf": 0, "startDeviceLocation": "150999061", "destDeviceLocation": "150999119", "arriveTime": 1770303740}]}]}, {"directDeviceLocation": "150999061", "direction": [{"isWeekDay": 0, "timetables": [{"isHalf": 0, "startDeviceLocation": "150999119", "destDeviceLocation": "150999061", "arriveTime": 1769896553}, {"isHalf": 0, "startDeviceLocation": "150999119", "destDeviceLocation": "150999061", "arriveTime": 1769897153}, {"isHalf": 0, "startDeviceLocation": "150999119", "destDeviceLocation": "150999061", "arriveTime": 1769897753}, {"isHalf": 0, "startDeviceLocation": "150999119", "destDeviceLocation": "150999061", "arriveTime": 1769898353}, {"isHalf": 0, "startDeviceLocation": "150999119", "destDeviceLocation": "150999061", "arriveTime": 1769898953}, {"isHalf": 0, "startDeviceLocation": "150999119", "destDeviceLocation": "150999061", "arriveTime": 1769899553}, {"isHalf": 0, "startDeviceLocation": "150999119", "destDeviceLocation": "150999061", "arriveTime": 1769900153}, {"isHalf": 0, "startDeviceLocation": "150999119", "destDeviceLocation": "150999061", "arriveTime": 1769900753}, {"isHalf": 0, "startDeviceLocation": "150999119", "destDeviceLocation": "150999061", "arriveTime": 1769901293}, {"isHalf": 0, "startDeviceLocation": "150999119", "destDeviceLocation": "150999061", "arriveTime": 1769901833}, {"isHalf": 0, "startDeviceLocation": "150999119", "destDeviceLocation": "150999061", "arriveTime": 1769902373}, {"isHalf": 0, "startDeviceLocation": "150999119", "destDeviceLocation": "150999061", "arriveTime": 1769902853}, {"isHalf": 0, "startDeviceLocation": "150999119", "destDeviceLocation": "150999061", "arriveTime": 1769903333}, {"isHalf": 0, "startDeviceLocation": "150999119", "destDeviceLocation": "150999061", "arriveTime": 1769903813}, {"isHalf": 0, "startDeviceLocation": "150999119", "destDeviceLocation": "150999061", "arriveTime": 1769904293}, {"isHalf": 0, "startDeviceLocation": "150999119", "destDeviceLocation": "150999061", "arriveTime": 1769904773}, {"isHalf": 0, "startDeviceLocation": "150999119", "destDeviceLocation": "150999061", "arriveTime": 1769905253}, {"isHalf": 0, "startDeviceLocation": "150999119", "destDeviceLocation": "150999061", "arriveTime": 1769905733}, {"isHalf": 0, "startDeviceLocation": "150999119", "destDeviceLocation": "150999061", "arriveTime": 1769906213}, {"isHalf": 0, "startDeviceLocation": "150999119", "destDeviceLocation": "150999061", "arriveTime": 1769906693}, {"isHalf": 0, "startDeviceLocation": "150999119", "destDeviceLocation": "150999061", "arriveTime": 1769907173}, {"isHalf": 0, "startDeviceLocation": "150999119", "destDeviceLocation": "150999061", "arriveTime": 1769907653}, {"isHalf": 0, "startDeviceLocation": "150999119", "destDeviceLocation": "150999061", "arriveTime": 1769908133}, {"isHalf": 0, "startDeviceLocation": "150999119", "destDeviceLocation": "150999061", "arriveTime": 1769908613}, {"isHalf": 0, "startDeviceLocation": "150999119", "destDeviceLocation": "150999061", "arriveTime": 1769909093}, {"isHalf": 0, "startDeviceLocation": "150999119", "destDeviceLocation": "150999061", "arriveTime": 1769909573}, {"isHalf": 0, "startDeviceLocation": "150999119", "destDeviceLocation": "150999061", "arriveTime": 1769910053}, {"isHalf": 0, "startDeviceLocation": "150999119", "destDeviceLocation": "150999061", "arriveTime": 1769910533}, {"isHalf": 0, "startDeviceLocation": "150999119", "destDeviceLocation": "150999061", "arriveTime": 1769911013}, {"isHalf": 0, "startDeviceLocation": "150999119", "destDeviceLocation": "150999061", "arriveTime": 1769911493}, {"isHalf": 0, "startDeviceLocation": "150999119", "destDeviceLocation": "150999061", "arriveTime": 1769911973}, {"isHalf": 0, "startDeviceLocation": "150999119", "destDeviceLocation": "150999061", "arriveTime": 1769912453}, {"isHalf": 0, "startDeviceLocation": "150999119", "destDeviceLocation": "150999061", "arriveTime": 1769912933}, {"isHalf": 0, "startDeviceLocation": "150999119", "destDeviceLocation": "150999061", "arriveTime": 1769913413}, {"isHalf": 0, "startDeviceLocation": "150999119", "destDeviceLocation": "150999061", "arriveTime": 1769913893}, {"isHalf": 0, "startDeviceLocation": "150999119", "destDeviceLocation": "150999061", "arriveTime": 1769914373}, {"isHalf": 0, "startDeviceLocation": "150999119", "destDeviceLocation": "150999061", "arriveTime": 1769914853}, {"isHalf": 0, "startDeviceLocation": "150999119", "destDeviceLocation": "150999061", "arriveTime": 1769915333}, {"isHalf": 0, "startDeviceLocation": "150999119", "destDeviceLocation": "150999061", "arriveTime": 1769915813}, {"isHalf": 0, "startDeviceLocation": "150999119", "destDeviceLocation": "150999061", "arriveTime": 1769916293}, {"isHalf": 0, "startDeviceLocation": "150999119", "destDeviceLocation": "150999061", "arriveTime": 1769916773}, {"isHalf": 0, "startDeviceLocation": "150999119", "destDeviceLocation": "150999061", "arriveTime": 1769917253}, {"isHalf": 0, "startDeviceLocation": "150999119", "destDeviceLocation": "150999061", "arriveTime": 1769917733}, {"isHalf": 0, "startDeviceLocation": "150999119", "destDeviceLocation": "150999061", "arriveTime": 1769918213}, {"isHalf": 0, "startDeviceLocation": "150999119", "destDeviceLocation": "150999061", "arriveTime": 1769918693}, {"isHalf": 0, "startDeviceLocation": "150999119", "destDeviceLocation": "150999061", "arriveTime": 1769919173}, {"isHalf": 0, "startDeviceLocation": "150999119", "destDeviceLocation": "150999061", "arriveTime": 1769919653}, {"isHalf": 0, "startDeviceLocation": "150999119", "destDeviceLocation": "150999061", "arriveTime": 1769920133}, {"isHalf": 0, "startDeviceLocation": "150999119", "destDeviceLocation": "150999061", "arriveTime": 1769920613}, {"isHalf": 0, "startDeviceLocation": "150999119", "destDeviceLocation": "150999061", "arriveTime": 1769921093}, {"isHalf": 0, "startDeviceLocation": "150999119", "destDeviceLocation": "150999061", "arriveTime": 1769921573}, {"isHalf": 0, "startDeviceLocation": "150999119", "destDeviceLocation": "150999061", "arriveTime": 1769922053}, {"isHalf": 0, "startDeviceLocation": "150999119", "destDeviceLocation": "150999061", "arriveTime": 1769922533}, {"isHalf": 0, "startDeviceLocation": "150999119", "destDeviceLocation": "150999061", "arriveTime": 1769923013}, {"isHalf": 0, "startDeviceLocation": "150999119", "destDeviceLocation": "150999061", "arriveTime": 1769923493}, {"isHalf": 0, "startDeviceLocation": "150999119", "destDeviceLocation": "150999061", "arriveTime": 1769923973}, {"isHalf": 0, "startDeviceLocation": "150999119", "destDeviceLocation": "150999061", "arriveTime": 1769924453}, {"isHalf": 0, "startDeviceLocation": "150999119", "destDeviceLocation": "150999061", "arriveTime": 1769924933}, {"isHalf": 0, "startDeviceLocation": "150999119", "destDeviceLocation": "150999061", "arriveTime": 1769925413}, {"isHalf": 0, "startDeviceLocation": "150999119", "destDeviceLocation": "150999061", "arriveTime": 1769925893}, {"isHalf": 0, "startDeviceLocation": "150999119", "destDeviceLocation": "150999061", "arriveTime": 1769926373}, {"isHalf": 0, "startDeviceLocation": "150999119", "destDeviceLocation": "150999061", "arriveTime": 1769926853}, {"isHalf": 0, "startDeviceLocation": "150999119", "destDeviceLocation": "150999061", "arriveTime": 1769927333}, {"isHalf": 0, "startDeviceLocation": "150999119", "destDeviceLocation": "150999061", "arriveTime": 1769927813}, {"isHalf": 0, "startDeviceLocation": "150999119", "destDeviceLocation": "150999061", "arriveTime": 1769928293}, {"isHalf": 0, "startDeviceLocation": "150999119", "destDeviceLocation": "150999061", "arriveTime": 1769928773}, {"isHalf": 0, "startDeviceLocation": "150999119", "destDeviceLocation": "150999061", "arriveTime": 1769929253}, {"isHalf": 0, "startDeviceLocation": "150999119", "destDeviceLocation": "150999061", "arriveTime": 1769929733}, {"isHalf": 0, "startDeviceLocation": "150999119", "destDeviceLocation": "150999061", "arriveTime": 1769930213}, {"isHalf": 0, "startDeviceLocation": "150999119", "destDeviceLocation": "150999061", "arriveTime": 1769930693}, {"isHalf": 0, "startDeviceLocation": "150999119", "destDeviceLocation": "150999061", "arriveTime": 1769931173}, {"isHalf": 0, "startDeviceLocation": "150999119", "destDeviceLocation": "150999061", "arriveTime": 1769931653}, {"isHalf": 0, "startDeviceLocation": "150999119", "destDeviceLocation": "150999061", "arriveTime": 1769932133}, {"isHalf": 0, "startDeviceLocation": "150999119", "destDeviceLocation": "150999061", "arriveTime": 1769932613}, {"isHalf": 0, "startDeviceLocation": "150999119", "destDeviceLocation": "150999061", "arriveTime": 1769933093}, {"isHalf": 0, "startDeviceLocation": "150999119", "destDeviceLocation": "150999061", "arriveTime": 1769933573}, {"isHalf": 0, "startDeviceLocation": "150999119", "destDeviceLocation": "150999061", "arriveTime": 1769934053}, {"isHalf": 0, "startDeviceLocation": "150999119", "destDeviceLocation": "150999061", "arriveTime": 1769934533}, {"isHalf": 0, "startDeviceLocation": "150999119", "destDeviceLocation": "150999061", "arriveTime": 1769935013}, {"isHalf": 0, "startDeviceLocation": "150999119", "destDeviceLocation": "150999061", "arriveTime": 1769935493}, {"isHalf": 0, "startDeviceLocation": "150999119", "destDeviceLocation": "150999061", "arriveTime": 1769935973}, {"isHalf": 0, "startDeviceLocation": "150999119", "destDeviceLocation": "150999061", "arriveTime": 1769936453}, {"isHalf": 0, "startDeviceLocation": "150999119", "destDeviceLocation": "150999061", "arriveTime": 1769936933}, {"isHalf": 0, "startDeviceLocation": "150999119", "destDeviceLocation": "150999061", "arriveTime": 1769937413}, {"isHalf": 0, "startDeviceLocation": "150999119", "destDeviceLocation": "150999061", "arriveTime": 1769937893}, {"isHalf": 0, "startDeviceLocation": "150999119", "destDeviceLocation": "150999061", "arriveTime": 1769938373}, {"isHalf": 0, "startDeviceLocation": "150999119", "destDeviceLocation": "150999061", "arriveTime": 1769938853}, {"isHalf": 0, "startDeviceLocation": "150999119", "destDeviceLocation": "150999061", "arriveTime": 1769939333}, {"isHalf": 0, "startDeviceLocation": "150999119", "destDeviceLocation": "150999061", "arriveTime": 1769939813}, {"isHalf": 0, "startDeviceLocation": "150999119", "destDeviceLocation": "150999061", "arriveTime": 1769940293}, {"isHalf": 0, "startDeviceLocation": "150999119", "destDeviceLocation": "150999061", "arriveTime": 1769940773}, {"isHalf": 0, "startDeviceLocation": "150999119", "destDeviceLocation": "150999061", "arriveTime": 1769941253}, {"isHalf": 0, "startDeviceLocation": "150999119", "destDeviceLocation": "150999061", "arriveTime": 1769941733}, {"isHalf": 0, "startDeviceLocation": "150999119", "destDeviceLocation": "150999061", "arriveTime": 1769942213}, {"isHalf": 0, "startDeviceLocation": "150999119", "destDeviceLocation": "150999061", "arriveTime": 1769942693}, {"isHalf": 0, "startDeviceLocation": "150999119", "destDeviceLocation": "150999061", "arriveTime": 1769943173}, {"isHalf": 0, "startDeviceLocation": "150999119", "destDeviceLocation": "150999061", "arriveTime": 1769943653}, {"isHalf": 0, "startDeviceLocation": "150999119", "destDeviceLocation": "150999061", "arriveTime": 1769944133}, {"isHalf": 0, "startDeviceLocation": "150999119", "destDeviceLocation": "150999061", "arriveTime": 1769944613}, {"isHalf": 0, "startDeviceLocation": "150999119", "destDeviceLocation": "150999061", "arriveTime": 1769945093}, {"isHalf": 0, "startDeviceLocation": "150999119", "destDeviceLocation": "150999061", "arriveTime": 1769945573}, {"isHalf": 0, "startDeviceLocation": "150999119", "destDeviceLocation": "150999061", "arriveTime": 1769946053}, {"isHalf": 0, "startDeviceLocation": "150999119", "destDeviceLocation": "150999061", "arriveTime": 1769946533}, {"isHalf": 0, "startDeviceLocation": "150999119", "destDeviceLocation": "150999061", "arriveTime": 1769947013}, {"isHalf": 0, "startDeviceLocation": "150999119", "destDeviceLocation": "150999061", "arriveTime": 1769947493}, {"isHalf": 0, "startDeviceLocation": "150999119", "destDeviceLocation": "150999061", "arriveTime": 1769947973}, {"isHalf": 0, "startDeviceLocation": "150999119", "destDeviceLocation": "150999061", "arriveTime": 1769948453}, {"isHalf": 0, "startDeviceLocation": "150999119", "destDeviceLocation": "150999061", "arriveTime": 1769948933}, {"isHalf": 0, "startDeviceLocation": "150999119", "destDeviceLocation": "150999061", "arriveTime": 1769949413}, {"isHalf": 0, "startDeviceLocation": "150999119", "destDeviceLocation": "150999061", "arriveTime": 1769949893}, {"isHalf": 0, "startDeviceLocation": "150999119", "destDeviceLocation": "150999061", "arriveTime": 1769950373}, {"isHalf": 0, "startDeviceLocation": "150999119", "destDeviceLocation": "150999061", "arriveTime": 1769950853}, {"isHalf": 0, "startDeviceLocation": "150999119", "destDeviceLocation": "150999061", "arriveTime": 1769951333}, {"isHalf": 0, "startDeviceLocation": "150999119", "destDeviceLocation": "150999061", "arriveTime": 1769951813}, {"isHalf": 0, "startDeviceLocation": "150999119", "destDeviceLocation": "150999061", "arriveTime": 1769952293}, {"isHalf": 0, "startDeviceLocation": "150999119", "destDeviceLocation": "150999061", "arriveTime": 1769952773}, {"isHalf": 0, "startDeviceLocation": "150999119", "destDeviceLocation": "150999061", "arriveTime": 1769953253}, {"isHalf": 0, "startDeviceLocation": "150999119", "destDeviceLocation": "150999061", "arriveTime": 1769953733}, {"isHalf": 0, "startDeviceLocation": "150999119", "destDeviceLocation": "150999061", "arriveTime": 1769954213}, {"isHalf": 0, "startDeviceLocation": "150999119", "destDeviceLocation": "150999061", "arriveTime": 1769954693}, {"isHalf": 0, "startDeviceLocation": "150999119", "destDeviceLocation": "150999061", "arriveTime": 1769955173}, {"isHalf": 0, "startDeviceLocation": "150999119", "destDeviceLocation": "150999061", "arriveTime": 1769955653}, {"isHalf": 0, "startDeviceLocation": "150999119", "destDeviceLocation": "150999061", "arriveTime": 1769956133}, {"isHalf": 0, "startDeviceLocation": "150999119", "destDeviceLocation": "150999061", "arriveTime": 1769956673}, {"isHalf": 0, "startDeviceLocation": "150999119", "destDeviceLocation": "150999061", "arriveTime": 1769957213}, {"isHalf": 0, "startDeviceLocation": "150999119", "destDeviceLocation": "150999061", "arriveTime": 1769957753}, {"isHalf": 0, "startDeviceLocation": "150999119", "destDeviceLocation": "150999061", "arriveTime": 1769958293}, {"isHalf": 0, "startDeviceLocation": "150999119", "destDeviceLocation": "150999061", "arriveTime": 1769958893}, {"isHalf": 0, "startDeviceLocation": "150999119", "destDeviceLocation": "150999061", "arriveTime": 1769959493}, {"isHalf": 0, "startDeviceLocation": "150999119", "destDeviceLocation": "150999061", "arriveTime": 1769960093}]}, {"isWeekDay": 1, "timetables": [{"isHalf": 0, "startDeviceLocation": "150999119", "destDeviceLocation": "150999061", "arriveTime": 1770242153}, {"isHalf": 0, "startDeviceLocation": "150999119", "destDeviceLocation": "150999061", "arriveTime": 1770242753}, {"isHalf": 0, "startDeviceLocation": "150999119", "destDeviceLocation": "150999061", "arriveTime": 1770243353}, {"isHalf": 0, "startDeviceLocation": "150999119", "destDeviceLocation": "150999061", "arriveTime": 1770243953}, {"isHalf": 0, "startDeviceLocation": "150999119", "destDeviceLocation": "150999061", "arriveTime": 1770244553}, {"isHalf": 0, "startDeviceLocation": "150999119", "destDeviceLocation": "150999061", "arriveTime": 1770245153}, {"isHalf": 0, "startDeviceLocation": "150999119", "destDeviceLocation": "150999061", "arriveTime": 1770245753}, {"isHalf": 0, "startDeviceLocation": "150999119", "destDeviceLocation": "150999061", "arriveTime": 1770246353}, {"isHalf": 0, "startDeviceLocation": "150999119", "destDeviceLocation": "150999061", "arriveTime": 1770246893}, {"isHalf": 0, "startDeviceLocation": "150999119", "destDeviceLocation": "150999061", "arriveTime": 1770247433}, {"isHalf": 0, "startDeviceLocation": "150999119", "destDeviceLocation": "150999061", "arriveTime": 1770247913}, {"isHalf": 0, "startDeviceLocation": "150999119", "destDeviceLocation": "150999061", "arriveTime": 1770248333}, {"isHalf": 0, "startDeviceLocation": "150999119", "destDeviceLocation": "150999061", "arriveTime": 1770248693}, {"isHalf": 0, "startDeviceLocation": "150999119", "destDeviceLocation": "150999061", "arriveTime": 1770249053}, {"isHalf": 0, "startDeviceLocation": "150999119", "destDeviceLocation": "150999061", "arriveTime": 1770249413}, {"isHalf": 0, "startDeviceLocation": "150999119", "destDeviceLocation": "150999061", "arriveTime": 1770249773}, {"isHalf": 0, "startDeviceLocation": "150999119", "destDeviceLocation": "150999061", "arriveTime": 1770250133}, {"isHalf": 0, "startDeviceLocation": "150999119", "destDeviceLocation": "150999061", "arriveTime": 1770250493}, {"isHalf": 0, "startDeviceLocation": "150999119", "destDeviceLocation": "150999061", "arriveTime": 1770250853}, {"isHalf": 0, "startDeviceLocation": "150999119", "destDeviceLocation": "150999061", "arriveTime": 1770251213}, {"isHalf": 0, "startDeviceLocation": "150999119", "destDeviceLocation": "150999061", "arriveTime": 1770251573}, {"isHalf": 0, "startDeviceLocation": "150999119", "destDeviceLocation": "150999061", "arriveTime": 1770251933}, {"isHalf": 0, "startDeviceLocation": "150999119", "destDeviceLocation": "150999061", "arriveTime": 1770252293}, {"isHalf": 0, "startDeviceLocation": "150999119", "destDeviceLocation": "150999061", "arriveTime": 1770252653}, {"isHalf": 0, "startDeviceLocation": "150999119", "destDeviceLocation": "150999061", "arriveTime": 1770253013}, {"isHalf": 0, "startDeviceLocation": "150999119", "destDeviceLocation": "150999061", "arriveTime": 1770253373}, {"isHalf": 0, "startDeviceLocation": "150999119", "destDeviceLocation": "150999061", "arriveTime": 1770253733}, {"isHalf": 0, "startDeviceLocation": "150999119", "destDeviceLocation": "150999061", "arriveTime": 1770254093}, {"isHalf": 0, "startDeviceLocation": "150999119", "destDeviceLocation": "150999061", "arriveTime": 1770254453}, {"isHalf": 0, "startDeviceLocation": "150999119", "destDeviceLocation": "150999061", "arriveTime": 1770254813}, {"isHalf": 0, "startDeviceLocation": "150999119", "destDeviceLocation": "150999061", "arriveTime": 1770255173}, {"isHalf": 0, "startDeviceLocation": "150999119", "destDeviceLocation": "150999061", "arriveTime": 1770255533}, {"isHalf": 0, "startDeviceLocation": "150999119", "destDeviceLocation": "150999061", "arriveTime": 1770255953}, {"isHalf": 0, "startDeviceLocation": "150999119", "destDeviceLocation": "150999061", "arriveTime": 1770256373}, {"isHalf": 0, "startDeviceLocation": "150999119", "destDeviceLocation": "150999061", "arriveTime": 1770256793}, {"isHalf": 0, "startDeviceLocation": "150999119", "destDeviceLocation": "150999061", "arriveTime": 1770257213}, {"isHalf": 0, "startDeviceLocation": "150999119", "destDeviceLocation": "150999061", "arriveTime": 1770257633}, {"isHalf": 0, "startDeviceLocation": "150999119", "destDeviceLocation": "150999061", "arriveTime": 1770258053}, {"isHalf": 0, "startDeviceLocation": "150999119", "destDeviceLocation": "150999061", "arriveTime": 1770258473}, {"isHalf": 0, "startDeviceLocation": "150999119", "destDeviceLocation": "150999061", "arriveTime": 1770258893}, {"isHalf": 0, "startDeviceLocation": "150999119", "destDeviceLocation": "150999061", "arriveTime": 1770259313}, {"isHalf": 0, "startDeviceLocation": "150999119", "destDeviceLocation": "150999061", "arriveTime": 1770259733}, {"isHalf": 0, "startDeviceLocation": "150999119", "destDeviceLocation": "150999061", "arriveTime": 1770260153}, {"isHalf": 0, "startDeviceLocation": "150999119", "destDeviceLocation": "150999061", "arriveTime": 1770260633}, {"isHalf": 0, "startDeviceLocation": "150999119", "destDeviceLocation": "150999061", "arriveTime": 1770261113}, {"isHalf": 0, "startDeviceLocation": "150999119", "destDeviceLocation": "150999061", "arriveTime": 1770261593}, {"isHalf": 0, "startDeviceLocation": "150999119", "destDeviceLocation": "150999061", "arriveTime": 1770262073}, {"isHalf": 0, "startDeviceLocation": "150999119", "destDeviceLocation": "150999061", "arriveTime": 1770262553}, {"isHalf": 0, "startDeviceLocation": "150999119", "destDeviceLocation": "150999061", "arriveTime": 1770263033}, {"isHalf": 0, "startDeviceLocation": "150999119", "destDeviceLocation": "150999061", "arriveTime": 1770263513}, {"isHalf": 0, "startDeviceLocation": "150999119", "destDeviceLocation": "150999061", "arriveTime": 1770263993}, {"isHalf": 0, "startDeviceLocation": "150999119", "destDeviceLocation": "150999061", "arriveTime": 1770264473}, {"isHalf": 0, "startDeviceLocation": "150999119", "destDeviceLocation": "150999061", "arriveTime": 1770264953}, {"isHalf": 0, "startDeviceLocation": "150999119", "destDeviceLocation": "150999061", "arriveTime": 1770265433}, {"isHalf": 0, "startDeviceLocation": "150999119", "destDeviceLocation": "150999061", "arriveTime": 1770265913}, {"isHalf": 0, "startDeviceLocation": "150999119", "destDeviceLocation": "150999061", "arriveTime": 1770266393}, {"isHalf": 0, "startDeviceLocation": "150999119", "destDeviceLocation": "150999061", "arriveTime": 1770266873}, {"isHalf": 0, "startDeviceLocation": "150999119", "destDeviceLocation": "150999061", "arriveTime": 1770267353}, {"isHalf": 0, "startDeviceLocation": "150999119", "destDeviceLocation": "150999061", "arriveTime": 1770267833}, {"isHalf": 0, "startDeviceLocation": "150999119", "destDeviceLocation": "150999061", "arriveTime": 1770268313}, {"isHalf": 0, "startDeviceLocation": "150999119", "destDeviceLocation": "150999061", "arriveTime": 1770268793}, {"isHalf": 0, "startDeviceLocation": "150999119", "destDeviceLocation": "150999061", "arriveTime": 1770269273}, {"isHalf": 0, "startDeviceLocation": "150999119", "destDeviceLocation": "150999061", "arriveTime": 1770269753}, {"isHalf": 0, "startDeviceLocation": "150999119", "destDeviceLocation": "150999061", "arriveTime": 1770270233}, {"isHalf": 0, "startDeviceLocation": "150999119", "destDeviceLocation": "150999061", "arriveTime": 1770270713}, {"isHalf": 0, "startDeviceLocation": "150999119", "destDeviceLocation": "150999061", "arriveTime": 1770271193}, {"isHalf": 0, "startDeviceLocation": "150999119", "destDeviceLocation": "150999061", "arriveTime": 1770271673}, {"isHalf": 0, "startDeviceLocation": "150999119", "destDeviceLocation": "150999061", "arriveTime": 1770272153}, {"isHalf": 0, "startDeviceLocation": "150999119", "destDeviceLocation": "150999061", "arriveTime": 1770272633}, {"isHalf": 0, "startDeviceLocation": "150999119", "destDeviceLocation": "150999061", "arriveTime": 1770273113}, {"isHalf": 0, "startDeviceLocation": "150999119", "destDeviceLocation": "150999061", "arriveTime": 1770273593}, {"isHalf": 0, "startDeviceLocation": "150999119", "destDeviceLocation": "150999061", "arriveTime": 1770274073}, {"isHalf": 0, "startDeviceLocation": "150999119", "destDeviceLocation": "150999061", "arriveTime": 1770274553}, {"isHalf": 0, "startDeviceLocation": "150999119", "destDeviceLocation": "150999061", "arriveTime": 1770275033}, {"isHalf": 0, "startDeviceLocation": "150999119", "destDeviceLocation": "150999061", "arriveTime": 1770275513}, {"isHalf": 0, "startDeviceLocation": "150999119", "destDeviceLocation": "150999061", "arriveTime": 1770275993}, {"isHalf": 0, "startDeviceLocation": "150999119", "destDeviceLocation": "150999061", "arriveTime": 1770276473}, {"isHalf": 0, "startDeviceLocation": "150999119", "destDeviceLocation": "150999061", "arriveTime": 1770276953}, {"isHalf": 0, "startDeviceLocation": "150999119", "destDeviceLocation": "150999061", "arriveTime": 1770277433}, {"isHalf": 0, "startDeviceLocation": "150999119", "destDeviceLocation": "150999061", "arriveTime": 1770277913}, {"isHalf": 0, "startDeviceLocation": "150999119", "destDeviceLocation": "150999061", "arriveTime": 1770278393}, {"isHalf": 0, "startDeviceLocation": "150999119", "destDeviceLocation": "150999061", "arriveTime": 1770278873}, {"isHalf": 0, "startDeviceLocation": "150999119", "destDeviceLocation": "150999061", "arriveTime": 1770279353}, {"isHalf": 0, "startDeviceLocation": "150999119", "destDeviceLocation": "150999061", "arriveTime": 1770279833}, {"isHalf": 0, "startDeviceLocation": "150999119", "destDeviceLocation": "150999061", "arriveTime": 1770280313}, {"isHalf": 0, "startDeviceLocation": "150999119", "destDeviceLocation": "150999061", "arriveTime": 1770280793}, {"isHalf": 0, "startDeviceLocation": "150999119", "destDeviceLocation": "150999061", "arriveTime": 1770281273}, {"isHalf": 0, "startDeviceLocation": "150999119", "destDeviceLocation": "150999061", "arriveTime": 1770281753}, {"isHalf": 0, "startDeviceLocation": "150999119", "destDeviceLocation": "150999061", "arriveTime": 1770282233}, {"isHalf": 0, "startDeviceLocation": "150999119", "destDeviceLocation": "150999061", "arriveTime": 1770282713}, {"isHalf": 0, "startDeviceLocation": "150999119", "destDeviceLocation": "150999061", "arriveTime": 1770283193}, {"isHalf": 0, "startDeviceLocation": "150999119", "destDeviceLocation": "150999061", "arriveTime": 1770283673}, {"isHalf": 0, "startDeviceLocation": "150999119", "destDeviceLocation": "150999061", "arriveTime": 1770284153}, {"isHalf": 0, "startDeviceLocation": "150999119", "destDeviceLocation": "150999061", "arriveTime": 1770284633}, {"isHalf": 0, "startDeviceLocation": "150999119", "destDeviceLocation": "150999061", "arriveTime": 1770285113}, {"isHalf": 0, "startDeviceLocation": "150999119", "destDeviceLocation": "150999061", "arriveTime": 1770285593}, {"isHalf": 0, "startDeviceLocation": "150999119", "destDeviceLocation": "150999061", "arriveTime": 1770286073}, {"isHalf": 0, "startDeviceLocation": "150999119", "destDeviceLocation": "150999061", "arriveTime": 1770286553}, {"isHalf": 0, "startDeviceLocation": "150999119", "destDeviceLocation": "150999061", "arriveTime": 1770286973}, {"isHalf": 0, "startDeviceLocation": "150999119", "destDeviceLocation": "150999061", "arriveTime": 1770287333}, {"isHalf": 0, "startDeviceLocation": "150999119", "destDeviceLocation": "150999061", "arriveTime": 1770287693}, {"isHalf": 0, "startDeviceLocation": "150999119", "destDeviceLocation": "150999061", "arriveTime": 1770288053}, {"isHalf": 0, "startDeviceLocation": "150999119", "destDeviceLocation": "150999061", "arriveTime": 1770288413}, {"isHalf": 0, "startDeviceLocation": "150999119", "destDeviceLocation": "150999061", "arriveTime": 1770288773}, {"isHalf": 0, "startDeviceLocation": "150999119", "destDeviceLocation": "150999061", "arriveTime": 1770289133}, {"isHalf": 0, "startDeviceLocation": "150999119", "destDeviceLocation": "150999061", "arriveTime": 1770289493}, {"isHalf": 0, "startDeviceLocation": "150999119", "destDeviceLocation": "150999061", "arriveTime": 1770289853}, {"isHalf": 0, "startDeviceLocation": "150999119", "destDeviceLocation": "150999061", "arriveTime": 1770290213}, {"isHalf": 0, "startDeviceLocation": "150999119", "destDeviceLocation": "150999061", "arriveTime": 1770290573}, {"isHalf": 0, "startDeviceLocation": "150999119", "destDeviceLocation": "150999061", "arriveTime": 1770290933}, {"isHalf": 0, "startDeviceLocation": "150999119", "destDeviceLocation": "150999061", "arriveTime": 1770291293}, {"isHalf": 0, "startDeviceLocation": "150999119", "destDeviceLocation": "150999061", "arriveTime": 1770291653}, {"isHalf": 0, "startDeviceLocation": "150999119", "destDeviceLocation": "150999061", "arriveTime": 1770292013}, {"isHalf": 0, "startDeviceLocation": "150999119", "destDeviceLocation": "150999061", "arriveTime": 1770292373}, {"isHalf": 0, "startDeviceLocation": "150999119", "destDeviceLocation": "150999061", "arriveTime": 1770292733}, {"isHalf": 0, "startDeviceLocation": "150999119", "destDeviceLocation": "150999061", "arriveTime": 1770293093}, {"isHalf": 0, "startDeviceLocation": "150999119", "destDeviceLocation": "150999061", "arriveTime": 1770293453}, {"isHalf": 0, "startDeviceLocation": "150999119", "destDeviceLocation": "150999061", "arriveTime": 1770293813}, {"isHalf": 0, "startDeviceLocation": "150999119", "destDeviceLocation": "150999061", "arriveTime": 1770294173}, {"isHalf": 0, "startDeviceLocation": "150999119", "destDeviceLocation": "150999061", "arriveTime": 1770294593}, {"isHalf": 0, "startDeviceLocation": "150999119", "destDeviceLocation": "150999061", "arriveTime": 1770295013}, {"isHalf": 0, "startDeviceLocation": "150999119", "destDeviceLocation": "150999061", "arriveTime": 1770295433}, {"isHalf": 0, "startDeviceLocation": "150999119", "destDeviceLocation": "150999061", "arriveTime": 1770295853}, {"isHalf": 0, "startDeviceLocation": "150999119", "destDeviceLocation": "150999061", "arriveTime": 1770296273}, {"isHalf": 0, "startDeviceLocation": "150999119", "destDeviceLocation": "150999061", "arriveTime": 1770296693}, {"isHalf": 0, "startDeviceLocation": "150999119", "destDeviceLocation": "150999061", "arriveTime": 1770297113}, {"isHalf": 0, "startDeviceLocation": "150999119", "destDeviceLocation": "150999061", "arriveTime": 1770297533}, {"isHalf": 0, "startDeviceLocation": "150999119", "destDeviceLocation": "150999061", "arriveTime": 1770298013}, {"isHalf": 0, "startDeviceLocation": "150999119", "destDeviceLocation": "150999061", "arriveTime": 1770298493}, {"isHalf": 0, "startDeviceLocation": "150999119", "destDeviceLocation": "150999061", "arriveTime": 1770298973}, {"isHalf": 0, "startDeviceLocation": "150999119", "destDeviceLocation": "150999061", "arriveTime": 1770299453}, {"isHalf": 0, "startDeviceLocation": "150999119", "destDeviceLocation": "150999061", "arriveTime": 1770299933}, {"isHalf": 0, "startDeviceLocation": "150999119", "destDeviceLocation": "150999061", "arriveTime": 1770300413}, {"isHalf": 0, "startDeviceLocation": "150999119", "destDeviceLocation": "150999061", "arriveTime": 1770300893}, {"isHalf": 0, "startDeviceLocation": "150999119", "destDeviceLocation": "150999061", "arriveTime": 1770301373}, {"isHalf": 0, "startDeviceLocation": "150999119", "destDeviceLocation": "150999061", "arriveTime": 1770301853}, {"isHalf": 0, "startDeviceLocation": "150999119", "destDeviceLocation": "150999061", "arriveTime": 1770302333}, {"isHalf": 0, "startDeviceLocation": "150999119", "destDeviceLocation": "150999061", "arriveTime": 1770302813}, {"isHalf": 0, "startDeviceLocation": "150999119", "destDeviceLocation": "150999061", "arriveTime": 1770303353}, {"isHalf": 0, "startDeviceLocation": "150999119", "destDeviceLocation": "150999061", "arriveTime": 1770303893}, {"isHalf": 0, "startDeviceLocation": "150999119", "destDeviceLocation": "150999061", "arriveTime": 1770304493}, {"isHalf": 0, "startDeviceLocation": "150999119", "destDeviceLocation": "150999061", "arriveTime": 1770305093}, {"isHalf": 0, "startDeviceLocation": "150999119", "destDeviceLocation": "150999061", "arriveTime": 1770305693}]}]}]}]